[{"code":"20361","old_zip_code":"393  ","zip_code":"3930000","prefecture_kana":"ﾅｶﾞﾉｹﾝ","city_kana":"ｽﾜｸﾞﾝｼﾓｽﾜﾏﾁ","town_kana":"ｲｶﾆｹｲｻｲｶﾞﾅｲﾊﾞｱｲ","prefecture":"長野県","city":"諏訪郡下諏訪町","town":"以下に掲載がない場合","has_multiple_zip_codes":"0","needs_koaza":"0","has_chome":"0","shares_zip_code":"0","update_status":"0","change_reason":"0"},{"code":"20361","old_zip_code":"393  ","zip_code":"3930066","prefecture_kana":"ﾅｶﾞﾉｹﾝ","city_kana":"ｽﾜｸﾞﾝｼﾓｽﾜﾏﾁ","town_kana":"ｱｹﾎﾞﾉﾁｮｳ","prefecture":"長野県","city":"諏訪郡下諏訪町","town":"曙町","has_multiple_zip_codes":"0","needs_koaza":"0","has_chome":"0","shares_zip_code":"0","update_status":"0","change_reason":"0"},{"code":"20361","old_zip_code":"393  ","zip_code":"3930068","prefecture_kana":"ﾅｶﾞﾉｹﾝ","city_kana":"ｽﾜｸﾞﾝｼﾓｽﾜﾏﾁ","town_kana":"ｶｽｶﾞﾁｮｳ","prefecture":"長野県","city":"諏訪郡下諏訪町","town":"春日町","has_multiple_zip_codes":"0","needs_koaza":"0","has_chome":"0","shares_zip_code":"0","update_status":"0","change_reason":"0"},{"code":"20361","old_zip_code":"393  ","zip_code":"3930052","prefecture_kana":"ﾅｶﾞﾉｹﾝ","city_kana":"ｽﾜｸﾞﾝｼﾓｽﾜﾏﾁ","town_kana":"ｶﾐｸﾎﾞ","prefecture":"長野県","city":"諏訪郡下諏訪町","town":"上久保","has_multiple_zip_codes":"0","needs_koaza":"0","has_chome":"0","shares_zip_code":"0","update_status":"0","change_reason":"0"},{"code":"20361","old_zip_code":"393  ","zip_code":"3930053","prefecture_kana":"ﾅｶﾞﾉｹﾝ","city_kana":"ｽﾜｸﾞﾝｼﾓｽﾜﾏﾁ","town_kana":"ｶﾐﾊﾞｯﾊﾟ","prefecture":"長野県","city":"諏訪郡下諏訪町","town":"上馬場","has_multiple_zip_codes":"0","needs_koaza":"0","has_chome":"0","shares_zip_code":"0","update_status":"0","change_reason":"0"},{"code":"20361","old_zip_code":"393  ","zip_code":"3930042","prefecture_kana":"ﾅｶﾞﾉｹﾝ","city_kana":"ｽﾜｸﾞﾝｼﾓｽﾜﾏﾁ","town_kana":"ｷﾀｼｵｳ","prefecture":"長野県","city":"諏訪郡下諏訪町","town":"北四王","has_multiple_zip_codes":"0","needs_koaza":"0","has_chome":"0","shares_zip_code":"0","update_status":"0","change_reason":"0"},{"code":"20361","old_zip_code":"393  ","zip_code":"3930014","prefecture_kana":"ﾅｶﾞﾉｹﾝ","city_kana":"ｽﾜｸﾞﾝｼﾓｽﾜﾏﾁ","town_kana":"ｷﾉｼﾀ","prefecture":"長野県","city":"諏訪郡下諏訪町","town":"木の下","has_multiple_zip_codes":"0","needs_koaza":"0","has_chome":"0","shares_zip_code":"0","update_status":"0","change_reason":"0"},{"code":"20361","old_zip_code":"393  ","zip_code":"3930026","prefecture_kana":"ﾅｶﾞﾉｹﾝ","city_kana":"ｽﾜｸﾞﾝｼﾓｽﾜﾏﾁ","town_kana":"ｸﾎﾞｶｲﾄﾞｳ","prefecture":"長野県","city":"諏訪郡下諏訪町","town":"久保海道","has_multiple_zip_codes":"0","needs_koaza":"0","has_chome":"0","shares_zip_code":"0","update_status":"0","change_reason":"0"},{"code":"20361","old_zip_code":"393  ","zip_code":"3930024","prefecture_kana":"ﾅｶﾞﾉｹﾝ","city_kana":"ｽﾜｸﾞﾝｼﾓｽﾜﾏﾁ","town_kana":"ｺﾞｶﾝ","prefecture":"長野県","city":"諏訪郡下諏訪町","town":"五官","has_multiple_zip_codes":"0","needs_koaza":"0","has_chome":"0","shares_zip_code":"0","update_status":"0","change_reason":"0"},{"code":"20361","old_zip_code":"393  ","zip_code":"3930044","prefecture_kana":"ﾅｶﾞﾉｹﾝ","city_kana":"ｽﾜｸﾞﾝｼﾓｽﾜﾏﾁ","town_kana":"ｺﾊﾝﾁｮｳ","prefecture":"長野県","city":"諏訪郡下諏訪町","town":"湖畔町","has_multiple_zip_codes":"0","needs_koaza":"0","has_chome":"0","shares_zip_code":"0","update_status":"0","change_reason":"0"},{"code":"20361","old_zip_code":"393  ","zip_code":"3930013","prefecture_kana":"ﾅｶﾞﾉｹﾝ","city_kana":"ｽﾜｸﾞﾝｼﾓｽﾜﾏﾁ","town_kana":"ｺﾕﾉｳｴ","prefecture":"長野県","city":"諏訪郡下諏訪町","town":"小湯の上","has_multiple_zip_codes":"0","needs_koaza":"0","has_chome":"0","shares_zip_code":"0","update_status":"0","change_reason":"0"},{"code":"20361","old_zip_code":"393  ","zip_code":"3930084","prefecture_kana":"ﾅｶﾞﾉｹﾝ","city_kana":"ｽﾜｸﾞﾝｼﾓｽﾜﾏﾁ","town_kana":"ｻｶｴﾁｮｳ","prefecture":"長野県","city":"諏訪郡下諏訪町","town":"栄町","has_multiple_zip_codes":"0","needs_koaza":"0","has_chome":"0","shares_zip_code":"0","update_status":"0","change_reason":"0"},{"code":"20361","old_zip_code":"393  ","zip_code":"3930065","prefecture_kana":"ﾅｶﾞﾉｹﾝ","city_kana":"ｽﾜｸﾞﾝｼﾓｽﾜﾏﾁ","town_kana":"ｻｷｶﾞｹﾁｮｳ","prefecture":"長野県","city":"諏訪郡下諏訪町","town":"魁町","has_multiple_zip_codes":"0","needs_koaza":"0","has_chome":"0","shares_zip_code":"0","update_status":"0","change_reason":"0"},{"code":"20361","old_zip_code":"393  ","zip_code":"3930072","prefecture_kana":"ﾅｶﾞﾉｹﾝ","city_kana":"ｽﾜｸﾞﾝｼﾓｽﾜﾏﾁ","town_kana":"ｻｸﾗﾏﾁ","prefecture":"長野県","city":"諏訪郡下諏訪町","town":"桜町","has_multiple_zip_codes":"0","needs_koaza":"0","has_chome":"0","shares_zip_code":"0","update_status":"0","change_reason":"0"},{"code":"20361","old_zip_code":"393  ","zip_code":"3930086","prefecture_kana":"ﾅｶﾞﾉｹﾝ","city_kana":"ｽﾜｸﾞﾝｼﾓｽﾜﾏﾁ","town_kana":"ｼﾐｽﾞﾏﾁ","prefecture":"長野県","city":"諏訪郡下諏訪町","town":"清水町","has_multiple_zip_codes":"0","needs_koaza":"0","has_chome":"0","shares_zip_code":"0","update_status":"0","change_reason":"0"},{"code":"20361","old_zip_code":"393  ","zip_code":"3930007","prefecture_kana":"ﾅｶﾞﾉｹﾝ","city_kana":"ｽﾜｸﾞﾝｼﾓｽﾜﾏﾁ","town_kana":"ｼﾓﾔｼｷ","prefecture":"長野県","city":"諏訪郡下諏訪町","town":"下屋敷","has_multiple_zip_codes":"0","needs_koaza":"0","has_chome":"0","shares_zip_code":"0","update_status":"0","change_reason":"0"},{"code":"20361","old_zip_code":"393  ","zip_code":"3930011","prefecture_kana":"ﾅｶﾞﾉｹﾝ","city_kana":"ｽﾜｸﾞﾝｼﾓｽﾜﾏﾁ","town_kana":"ｼﾝﾏﾁｳｴ","prefecture":"長野県","city":"諏訪郡下諏訪町","town":"新町上","has_multiple_zip_codes":"0","needs_koaza":"0","has_chome":"0","shares_zip_code":"0","update_status":"0","change_reason":"0"},{"code":"20361","old_zip_code":"393  ","zip_code":"3930018","prefecture_kana":"ﾅｶﾞﾉｹﾝ","city_kana":"ｽﾜｸﾞﾝｼﾓｽﾜﾏﾁ","town_kana":"ｼﾝﾏﾁｼﾀ","prefecture":"長野県","city":"諏訪郡下諏訪町","town":"新町下","has_multiple_zip_codes":"0","needs_koaza":"0","has_chome":"0","shares_zip_code":"0","update_status":"0","change_reason":"0"},{"code":"20361","old_zip_code":"393  ","zip_code":"3930054","prefecture_kana":"ﾅｶﾞﾉｹﾝ","city_kana":"ｽﾜｸﾞﾝｼﾓｽﾜﾏﾁ","town_kana":"ｽｹﾞﾉﾏﾁ","prefecture":"長野県","city":"諏訪郡下諏訪町","town":"菅野町","has_multiple_zip_codes":"0","needs_koaza":"0","has_chome":"0","shares_zip_code":"0","update_status":"0","change_reason":"0"},{"code":"20361","old_zip_code":"393  ","zip_code":"3930022","prefecture_kana":"ﾅｶﾞﾉｹﾝ","city_kana":"ｽﾜｸﾞﾝｼﾓｽﾜﾏﾁ","town_kana":"ｾｷﾔ","prefecture":"長野県","city":"諏訪郡下諏訪町","town":"関屋","has_multiple_zip_codes":"0","needs_koaza":"0","has_chome":"0","shares_zip_code":"0","update_status":"0","change_reason":"0"},{"code":"20361","old_zip_code":"393  ","zip_code":"3930051","prefecture_kana":"ﾅｶﾞﾉｹﾝ","city_kana":"ｽﾜｸﾞﾝｼﾓｽﾜﾏﾁ","town_kana":"ﾀｲｼｬﾄﾞｵﾘ","prefecture":"長野県","city":"諏訪郡下諏訪町","town":"大社通","has_multiple_zip_codes":"0","needs_koaza":"0","has_chome":"0","shares_zip_code":"0","update_status":"0","change_reason":"0"},{"code":"20361","old_zip_code":"393  ","zip_code":"3930092","prefecture_kana":"ﾅｶﾞﾉｹﾝ","city_kana":"ｽﾜｸﾞﾝｼﾓｽﾜﾏﾁ","town_kana":"ﾀﾞｲﾓﾝ","prefecture":"長野県","city":"諏訪郡下諏訪町","town":"大門","has_multiple_zip_codes":"0","needs_koaza":"0","has_chome":"0","shares_zip_code":"0","update_status":"0","change_reason":"0"},{"code":"20361","old_zip_code":"393  ","zip_code":"3930033","prefecture_kana":"ﾅｶﾞﾉｹﾝ","city_kana":"ｽﾜｸﾞﾝｼﾓｽﾜﾏﾁ","town_kana":"ﾀｶｷ","prefecture":"長野県","city":"諏訪郡下諏訪町","town":"高木","has_multiple_zip_codes":"0","needs_koaza":"0","has_chome":"0","shares_zip_code":"0","update_status":"0","change_reason":"0"},{"code":"20361","old_zip_code":"393  ","zip_code":"3930034","prefecture_kana":"ﾅｶﾞﾉｹﾝ","city_kana":"ｽﾜｸﾞﾝｼﾓｽﾜﾏﾁ","town_kana":"ﾀｶﾊﾏ","prefecture":"長野県","city":"諏訪郡下諏訪町","town":"高浜","has_multiple_zip_codes":"0","needs_koaza":"0","has_chome":"0","shares_zip_code":"0","update_status":"0","change_reason":"0"},{"code":"20361","old_zip_code":"393  ","zip_code":"3930021","prefecture_kana":"ﾅｶﾞﾉｹﾝ","city_kana":"ｽﾜｸﾞﾝｼﾓｽﾜﾏﾁ","town_kana":"ﾀｹｲ","prefecture":"長野県","city":"諏訪郡下諏訪町","town":"武居","has_multiple_zip_codes":"0","needs_koaza":"0","has_chome":"0","shares_zip_code":"0","update_status":"0","change_reason":"0"},{"code":"20361","old_zip_code":"393  ","zip_code":"3930015","prefecture_kana":"ﾅｶﾞﾉｹﾝ","city_kana":"ｽﾜｸﾞﾝｼﾓｽﾜﾏﾁ","town_kana":"ﾀﾂﾏﾁ","prefecture":"長野県","city":"諏訪郡下諏訪町","town":"立町","has_multiple_zip_codes":"0","needs_koaza":"0","has_chome":"0","shares_zip_code":"0","update_status":"0","change_reason":"0"},{"code":"20361","old_zip_code":"393  ","zip_code":"3930078","prefecture_kana":"ﾅｶﾞﾉｹﾝ","city_kana":"ｽﾜｸﾞﾝｼﾓｽﾜﾏﾁ","town_kana":"ﾀﾅｶﾏﾁ","prefecture":"長野県","city":"諏訪郡下諏訪町","town":"田中町","has_multiple_zip_codes":"0","needs_koaza":"0","has_chome":"0","shares_zip_code":"0","update_status":"0","change_reason":"0"},{"code":"20361","old_zip_code":"393  ","zip_code":"3930075","prefecture_kana":"ﾅｶﾞﾉｹﾝ","city_kana":"ｽﾜｸﾞﾝｼﾓｽﾜﾏﾁ","town_kana":"ﾁｭｳｵｳﾄﾞｵﾘ","prefecture":"長野県","city":"諏訪郡下諏訪町","town":"中央通","has_multiple_zip_codes":"0","needs_koaza":"0","has_chome":"0","shares_zip_code":"0","update_status":"0","change_reason":"0"},{"code":"20361","old_zip_code":"393  ","zip_code":"3930073","prefecture_kana":"ﾅｶﾞﾉｹﾝ","city_kana":"ｽﾜｸﾞﾝｼﾓｽﾜﾏﾁ","town_kana":"ﾂｶﾀﾞﾏﾁ","prefecture":"長野県","city":"諏訪郡下諏訪町","town":"塚田町","has_multiple_zip_codes":"0","needs_koaza":"0","has_chome":"0","shares_zip_code":"0","update_status":"0","change_reason":"0"},{"code":"20361","old_zip_code":"393  ","zip_code":"3930023","prefecture_kana":"ﾅｶﾞﾉｹﾝ","city_kana":"ｽﾜｸﾞﾝｼﾓｽﾜﾏﾁ","town_kana":"ﾄﾐｶﾞｵｶ","prefecture":"長野県","city":"諏訪郡下諏訪町","town":"富ケ丘","has_multiple_zip_codes":"0","needs_koaza":"0","has_chome":"0","shares_zip_code":"0","update_status":"0","change_reason":"0"},{"code":"20361","old_zip_code":"393  ","zip_code":"3930057","prefecture_kana":"ﾅｶﾞﾉｹﾝ","city_kana":"ｽﾜｸﾞﾝｼﾓｽﾜﾏﾁ","town_kana":"ﾄﾓﾉﾏﾁ","prefecture":"長野県","city":"諏訪郡下諏訪町","town":"友之町","has_multiple_zip_codes":"0","needs_koaza":"0","has_chome":"0","shares_zip_code":"0","update_status":"0","change_reason":"0"},{"code":"20361","old_zip_code":"393  ","zip_code":"3930001","prefecture_kana":"ﾅｶﾞﾉｹﾝ","city_kana":"ｽﾜｸﾞﾝｼﾓｽﾜﾏﾁ","town_kana":"ﾄﾖﾊｼ","prefecture":"長野県","city":"諏訪郡下諏訪町","town":"樋橋","has_multiple_zip_codes":"0","needs_koaza":"0","has_chome":"0","shares_zip_code":"0","update_status":"0","change_reason":"0"},{"code":"20361","old_zip_code":"393  ","zip_code":"3930064","prefecture_kana":"ﾅｶﾞﾉｹﾝ","city_kana":"ｽﾜｸﾞﾝｼﾓｽﾜﾏﾁ","town_kana":"ﾅｶｼｵﾁｮｳ","prefecture":"長野県","city":"諏訪郡下諏訪町","town":"中汐町","has_multiple_zip_codes":"0","needs_koaza":"0","has_chome":"0","shares_zip_code":"0","update_status":"0","change_reason":"0"},{"code":"20361","old_zip_code":"393  ","zip_code":"3930071","prefecture_kana":"ﾅｶﾞﾉｹﾝ","city_kana":"ｽﾜｸﾞﾝｼﾓｽﾜﾏﾁ","town_kana":"ﾅｶﾏﾁ","prefecture":"長野県","city":"諏訪郡下諏訪町","town":"仲町","has_multiple_zip_codes":"0","needs_koaza":"0","has_chome":"0","shares_zip_code":"0","update_status":"0","change_reason":"0"},{"code":"20361","old_zip_code":"393  ","zip_code":"3930047","prefecture_kana":"ﾅｶﾞﾉｹﾝ","city_kana":"ｽﾜｸﾞﾝｼﾓｽﾜﾏﾁ","town_kana":"ﾆｼｱｶｽﾅ","prefecture":"長野県","city":"諏訪郡下諏訪町","town":"西赤砂","has_multiple_zip_codes":"0","needs_koaza":"0","has_chome":"0","shares_zip_code":"0","update_status":"0","change_reason":"0"},{"code":"20361","old_zip_code":"393  ","zip_code":"3930041","prefecture_kana":"ﾅｶﾞﾉｹﾝ","city_kana":"ｽﾜｸﾞﾝｼﾓｽﾜﾏﾁ","town_kana":"ﾆｼｼｵｳ","prefecture":"長野県","city":"諏訪郡下諏訪町","town":"西四王","has_multiple_zip_codes":"0","needs_koaza":"0","has_chome":"0","shares_zip_code":"0","update_status":"0","change_reason":"0"},{"code":"20361","old_zip_code":"393  ","zip_code":"3930087","prefecture_kana":"ﾅｶﾞﾉｹﾝ","city_kana":"ｽﾜｸﾞﾝｼﾓｽﾜﾏﾁ","town_kana":"ﾆｼﾀｶﾉﾏﾁ","prefecture":"長野県","city":"諏訪郡下諏訪町","town":"西鷹野町","has_multiple_zip_codes":"0","needs_koaza":"0","has_chome":"0","shares_zip_code":"0","update_status":"0","change_reason":"0"},{"code":"20361","old_zip_code":"393  ","zip_code":"3930032","prefecture_kana":"ﾅｶﾞﾉｹﾝ","city_kana":"ｽﾜｸﾞﾝｼﾓｽﾜﾏﾁ","town_kana":"ﾆｼﾊﾏ","prefecture":"長野県","city":"諏訪郡下諏訪町","town":"西浜","has_multiple_zip_codes":"0","needs_koaza":"0","has_chome":"0","shares_zip_code":"0","update_status":"0","change_reason":"0"},{"code":"20361","old_zip_code":"393  ","zip_code":"3930082","prefecture_kana":"ﾅｶﾞﾉｹﾝ","city_kana":"ｽﾜｸﾞﾝｼﾓｽﾜﾏﾁ","town_kana":"ﾆｼﾔﾖｲﾁｮｳ","prefecture":"長野県","city":"諏訪郡下諏訪町","town":"西弥生町","has_multiple_zip_codes":"0","needs_koaza":"0","has_chome":"0","shares_zip_code":"0","update_status":"0","change_reason":"0"},{"code":"20361","old_zip_code":"393  ","zip_code":"3930035","prefecture_kana":"ﾅｶﾞﾉｹﾝ","city_kana":"ｽﾜｸﾞﾝｼﾓｽﾜﾏﾁ","town_kana":"ﾆｼﾕﾀｶ","prefecture":"長野県","city":"諏訪郡下諏訪町","town":"西豊","has_multiple_zip_codes":"0","needs_koaza":"0","has_chome":"0","shares_zip_code":"0","update_status":"0","change_reason":"0"},{"code":"20361","old_zip_code":"393  ","zip_code":"3930003","prefecture_kana":"ﾅｶﾞﾉｹﾝ","city_kana":"ｽﾜｸﾞﾝｼﾓｽﾜﾏﾁ","town_kana":"ﾊｷﾞｸﾗ","prefecture":"長野県","city":"諏訪郡下諏訪町","town":"萩倉","has_multiple_zip_codes":"0","needs_koaza":"0","has_chome":"0","shares_zip_code":"0","update_status":"0","change_reason":"0"},{"code":"20361","old_zip_code":"393  ","zip_code":"3930063","prefecture_kana":"ﾅｶﾞﾉｹﾝ","city_kana":"ｽﾜｸﾞﾝｼﾓｽﾜﾏﾁ","town_kana":"ﾊﾅｻｷﾁｮｳ","prefecture":"長野県","city":"諏訪郡下諏訪町","town":"花咲町","has_multiple_zip_codes":"0","needs_koaza":"0","has_chome":"0","shares_zip_code":"0","update_status":"0","change_reason":"0"},{"code":"20361","old_zip_code":"393  ","zip_code":"3930046","prefecture_kana":"ﾅｶﾞﾉｹﾝ","city_kana":"ｽﾜｸﾞﾝｼﾓｽﾜﾏﾁ","town_kana":"ﾋｶﾞｼｱｶｽﾅ","prefecture":"長野県","city":"諏訪郡下諏訪町","town":"東赤砂","has_multiple_zip_codes":"0","needs_koaza":"0","has_chome":"0","shares_zip_code":"0","update_status":"0","change_reason":"0"},{"code":"20361","old_zip_code":"393  ","zip_code":"3930043","prefecture_kana":"ﾅｶﾞﾉｹﾝ","city_kana":"ｽﾜｸﾞﾝｼﾓｽﾜﾏﾁ","town_kana":"ﾋｶﾞｼｼｵｳ","prefecture":"長野県","city":"諏訪郡下諏訪町","town":"東四王","has_multiple_zip_codes":"0","needs_koaza":"0","has_chome":"0","shares_zip_code":"0","update_status":"0","change_reason":"0"},{"code":"20361","old_zip_code":"393  ","zip_code":"3930085","prefecture_kana":"ﾅｶﾞﾉｹﾝ","city_kana":"ｽﾜｸﾞﾝｼﾓｽﾜﾏﾁ","town_kana":"ﾋｶﾞｼﾀｶﾉﾏﾁ","prefecture":"長野県","city":"諏訪郡下諏訪町","town":"東鷹野町","has_multiple_zip_codes":"0","needs_koaza":"0","has_chome":"0","shares_zip_code":"0","update_status":"0","change_reason":"0"},{"code":"20361","old_zip_code":"393  ","zip_code":"3930002","prefecture_kana":"ﾅｶﾞﾉｹﾝ","city_kana":"ｽﾜｸﾞﾝｼﾓｽﾜﾏﾁ","town_kana":"ﾋｶﾞｼﾏﾀ","prefecture":"長野県","city":"諏訪郡下諏訪町","town":"東俣","has_multiple_zip_codes":"0","needs_koaza":"0","has_chome":"0","shares_zip_code":"0","update_status":"0","change_reason":"0"},{"code":"20361","old_zip_code":"393  ","zip_code":"3930006","prefecture_kana":"ﾅｶﾞﾉｹﾝ","city_kana":"ｽﾜｸﾞﾝｼﾓｽﾜﾏﾁ","town_kana":"ﾋｶﾞｼﾏﾁｳｴ","prefecture":"長野県","city":"諏訪郡下諏訪町","town":"東町上","has_multiple_zip_codes":"0","needs_koaza":"0","has_chome":"0","shares_zip_code":"0","update_status":"0","change_reason":"0"},{"code":"20361","old_zip_code":"393  ","zip_code":"3930005","prefecture_kana":"ﾅｶﾞﾉｹﾝ","city_kana":"ｽﾜｸﾞﾝｼﾓｽﾜﾏﾁ","town_kana":"ﾋｶﾞｼﾏﾁﾅｶ","prefecture":"長野県","city":"諏訪郡下諏訪町","town":"東町中","has_multiple_zip_codes":"0","needs_koaza":"0","has_chome":"0","shares_zip_code":"0","update_status":"0","change_reason":"0"},{"code":"20361","old_zip_code":"393  ","zip_code":"3930004","prefecture_kana":"ﾅｶﾞﾉｹﾝ","city_kana":"ｽﾜｸﾞﾝｼﾓｽﾜﾏﾁ","town_kana":"ﾋｶﾞｼﾏﾁｼﾀ","prefecture":"長野県","city":"諏訪郡下諏訪町","town":"東町下","has_multiple_zip_codes":"0","needs_koaza":"0","has_chome":"0","shares_zip_code":"0","update_status":"0","change_reason":"0"},{"code":"20361","old_zip_code":"393  ","zip_code":"3930093","prefecture_kana":"ﾅｶﾞﾉｹﾝ","city_kana":"ｽﾜｸﾞﾝｼﾓｽﾜﾏﾁ","town_kana":"ﾋｶﾞｼﾔﾏﾀﾞ","prefecture":"長野県","city":"諏訪郡下諏訪町","town":"東山田","has_multiple_zip_codes":"0","needs_koaza":"0","has_chome":"0","shares_zip_code":"0","update_status":"0","change_reason":"0"},{"code":"20361","old_zip_code":"393  ","zip_code":"3930083","prefecture_kana":"ﾅｶﾞﾉｹﾝ","city_kana":"ｽﾜｸﾞﾝｼﾓｽﾜﾏﾁ","town_kana":"ﾋｶﾞｼﾔﾖｲﾁｮｳ","prefecture":"長野県","city":"諏訪郡下諏訪町","town":"東弥生町","has_multiple_zip_codes":"0","needs_koaza":"0","has_chome":"0","shares_zip_code":"0","update_status":"0","change_reason":"0"},{"code":"20361","old_zip_code":"393  ","zip_code":"3930031","prefecture_kana":"ﾅｶﾞﾉｹﾝ","city_kana":"ｽﾜｸﾞﾝｼﾓｽﾜﾏﾁ","town_kana":"ﾋｶﾞｼﾕﾀｶ","prefecture":"長野県","city":"諏訪郡下諏訪町","town":"東豊","has_multiple_zip_codes":"0","needs_koaza":"0","has_chome":"0","shares_zip_code":"0","update_status":"0","change_reason":"0"},{"code":"20361","old_zip_code":"393  ","zip_code":"3930062","prefecture_kana":"ﾅｶﾞﾉｹﾝ","city_kana":"ｽﾜｸﾞﾝｼﾓｽﾜﾏﾁ","town_kana":"ﾋﾗｻﾜﾁｮｳ","prefecture":"長野県","city":"諏訪郡下諏訪町","town":"平沢町","has_multiple_zip_codes":"0","needs_koaza":"0","has_chome":"0","shares_zip_code":"0","update_status":"0","change_reason":"0"},{"code":"20361","old_zip_code":"393  ","zip_code":"3930056","prefecture_kana":"ﾅｶﾞﾉｹﾝ","city_kana":"ｽﾜｸﾞﾝｼﾓｽﾜﾏﾁ","town_kana":"ﾋﾛｾﾁｮｳ","prefecture":"長野県","city":"諏訪郡下諏訪町","town":"広瀬町","has_multiple_zip_codes":"0","needs_koaza":"0","has_chome":"0","shares_zip_code":"0","update_status":"0","change_reason":"0"},{"code":"20361","old_zip_code":"393  ","zip_code":"3930055","prefecture_kana":"ﾅｶﾞﾉｹﾝ","city_kana":"ｽﾜｸﾞﾝｼﾓｽﾜﾏﾁ","town_kana":"ﾌｼﾞﾐﾁｮｳ","prefecture":"長野県","city":"諏訪郡下諏訪町","town":"富士見町","has_multiple_zip_codes":"0","needs_koaza":"0","has_chome":"0","shares_zip_code":"0","update_status":"0","change_reason":"0"},{"code":"20361","old_zip_code":"393  ","zip_code":"3930091","prefecture_kana":"ﾅｶﾞﾉｹﾝ","city_kana":"ｽﾜｸﾞﾝｼﾓｽﾜﾏﾁ","town_kana":"ﾎｼｶﾞｵｶ","prefecture":"長野県","city":"諏訪郡下諏訪町","town":"星が丘","has_multiple_zip_codes":"0","needs_koaza":"0","has_chome":"0","shares_zip_code":"0","update_status":"0","change_reason":"0"},{"code":"20361","old_zip_code":"393  ","zip_code":"3930025","prefecture_kana":"ﾅｶﾞﾉｹﾝ","city_kana":"ｽﾜｸﾞﾝｼﾓｽﾜﾏﾁ","town_kana":"ﾎﾝｺﾞｳ","prefecture":"長野県","city":"諏訪郡下諏訪町","town":"本郷","has_multiple_zip_codes":"0","needs_koaza":"0","has_chome":"0","shares_zip_code":"0","update_status":"0","change_reason":"0"},{"code":"20361","old_zip_code":"393  ","zip_code":"3930008","prefecture_kana":"ﾅｶﾞﾉｹﾝ","city_kana":"ｽﾜｸﾞﾝｼﾓｽﾜﾏﾁ","town_kana":"ﾏﾁﾔｼｷ","prefecture":"長野県","city":"諏訪郡下諏訪町","town":"町屋敷","has_multiple_zip_codes":"0","needs_koaza":"0","has_chome":"0","shares_zip_code":"0","update_status":"0","change_reason":"0"},{"code":"20361","old_zip_code":"393  ","zip_code":"3930061","prefecture_kana":"ﾅｶﾞﾉｹﾝ","city_kana":"ｽﾜｸﾞﾝｼﾓｽﾜﾏﾁ","town_kana":"ﾐﾀﾏﾁ","prefecture":"長野県","city":"諏訪郡下諏訪町","town":"御田町","has_multiple_zip_codes":"0","needs_koaza":"0","has_chome":"0","shares_zip_code":"0","update_status":"0","change_reason":"0"},{"code":"20361","old_zip_code":"393  ","zip_code":"3930074","prefecture_kana":"ﾅｶﾞﾉｹﾝ","city_kana":"ｽﾜｸﾞﾝｼﾓｽﾜﾏﾁ","town_kana":"ﾐﾄﾞﾘﾏﾁ","prefecture":"長野県","city":"諏訪郡下諏訪町","town":"緑町","has_multiple_zip_codes":"0","needs_koaza":"0","has_chome":"0","shares_zip_code":"0","update_status":"0","change_reason":"0"},{"code":"20361","old_zip_code":"393  ","zip_code":"3930045","prefecture_kana":"ﾅｶﾞﾉｹﾝ","city_kana":"ｽﾜｸﾞﾝｼﾓｽﾜﾏﾁ","town_kana":"ﾐﾅﾐｼｵｳ","prefecture":"長野県","city":"諏訪郡下諏訪町","town":"南四王","has_multiple_zip_codes":"0","needs_koaza":"0","has_chome":"0","shares_zip_code":"0","update_status":"0","change_reason":"0"},{"code":"20361","old_zip_code":"393  ","zip_code":"3930067","prefecture_kana":"ﾅｶﾞﾉｹﾝ","city_kana":"ｽﾜｸﾞﾝｼﾓｽﾜﾏﾁ","town_kana":"ﾔｷﾞﾋｶﾞｼ","prefecture":"長野県","city":"諏訪郡下諏訪町","town":"矢木東","has_multiple_zip_codes":"0","needs_koaza":"0","has_chome":"0","shares_zip_code":"0","update_status":"0","change_reason":"0"},{"code":"20361","old_zip_code":"393  ","zip_code":"3930076","prefecture_kana":"ﾅｶﾞﾉｹﾝ","city_kana":"ｽﾜｸﾞﾝｼﾓｽﾜﾏﾁ","town_kana":"ﾔｷﾞﾆｼ","prefecture":"長野県","city":"諏訪郡下諏訪町","town":"矢木西","has_multiple_zip_codes":"0","needs_koaza":"0","has_chome":"0","shares_zip_code":"0","update_status":"0","change_reason":"0"},{"code":"20361","old_zip_code":"393  ","zip_code":"3930077","prefecture_kana":"ﾅｶﾞﾉｹﾝ","city_kana":"ｽﾜｸﾞﾝｼﾓｽﾜﾏﾁ","town_kana":"ﾔｷﾞﾏﾁ","prefecture":"長野県","city":"諏訪郡下諏訪町","town":"矢木町","has_multiple_zip_codes":"0","needs_koaza":"0","has_chome":"0","shares_zip_code":"0","update_status":"0","change_reason":"0"},{"code":"20361","old_zip_code":"393  ","zip_code":"3930081","prefecture_kana":"ﾅｶﾞﾉｹﾝ","city_kana":"ｽﾜｸﾞﾝｼﾓｽﾜﾏﾁ","town_kana":"ﾔｼﾛﾋｶﾞｼﾏﾁ","prefecture":"長野県","city":"諏訪郡下諏訪町","town":"社東町","has_multiple_zip_codes":"0","needs_koaza":"0","has_chome":"0","shares_zip_code":"0","update_status":"0","change_reason":"0"},{"code":"20361","old_zip_code":"393  ","zip_code":"3930017","prefecture_kana":"ﾅｶﾞﾉｹﾝ","city_kana":"ｽﾜｸﾞﾝｼﾓｽﾜﾏﾁ","town_kana":"ﾕﾀﾞﾅｶﾏﾁ","prefecture":"長野県","city":"諏訪郡下諏訪町","town":"湯田仲町","has_multiple_zip_codes":"0","needs_koaza":"0","has_chome":"0","shares_zip_code":"0","update_status":"0","change_reason":"0"},{"code":"20361","old_zip_code":"393  ","zip_code":"3930016","prefecture_kana":"ﾅｶﾞﾉｹﾝ","city_kana":"ｽﾜｸﾞﾝｼﾓｽﾜﾏﾁ","town_kana":"ﾕﾀﾞﾏﾁ","prefecture":"長野県","city":"諏訪郡下諏訪町","town":"湯田町","has_multiple_zip_codes":"0","needs_koaza":"0","has_chome":"0","shares_zip_code":"0","update_status":"0","change_reason":"0"},{"code":"20361","old_zip_code":"393  ","zip_code":"3930012","prefecture_kana":"ﾅｶﾞﾉｹﾝ","city_kana":"ｽﾜｸﾞﾝｼﾓｽﾜﾏﾁ","town_kana":"ﾖｺﾏﾁ","prefecture":"長野県","city":"諏訪郡下諏訪町","town":"横町","has_multiple_zip_codes":"0","needs_koaza":"0","has_chome":"0","shares_zip_code":"0","update_status":"0","change_reason":"0"},{"code":"20361","old_zip_code":"393  ","zip_code":"3930019","prefecture_kana":"ﾅｶﾞﾉｹﾝ","city_kana":"ｽﾜｸﾞﾝｼﾓｽﾜﾏﾁ","town_kana":"ﾖｺﾏﾁｷﾉｼﾀ","prefecture":"長野県","city":"諏訪郡下諏訪町","town":"横町木の下","has_multiple_zip_codes":"0","needs_koaza":"0","has_chome":"0","shares_zip_code":"0","update_status":"0","change_reason":"0"}]