[{"code":"22210","old_zip_code":"417  ","zip_code":"4170000","prefecture_kana":"ｼｽﾞｵｶｹﾝ","city_kana":"ﾌｼﾞｼ","town_kana":"ｲｶﾆｹｲｻｲｶﾞﾅｲﾊﾞｱｲ","prefecture":"静岡県","city":"富士市","town":"以下に掲載がない場合","has_multiple_zip_codes":"0","needs_koaza":"0","has_chome":"0","shares_zip_code":"0","update_status":"0","change_reason":"0"},{"code":"22210","old_zip_code":"417  ","zip_code":"4170046","prefecture_kana":"ｼｽﾞｵｶｹﾝ","city_kana":"ﾌｼﾞｼ","town_kana":"ｱｵｼﾏ","prefecture":"静岡県","city":"富士市","town":"青島","has_multiple_zip_codes":"0","needs_koaza":"0","has_chome":"0","shares_zip_code":"0","update_status":"0","change_reason":"0"},{"code":"22210","old_zip_code":"417  ","zip_code":"4170047","prefecture_kana":"ｼｽﾞｵｶｹﾝ","city_kana":"ﾌｼﾞｼ","town_kana":"ｱｵｼﾏﾁｮｳ","prefecture":"静岡県","city":"富士市","town":"青島町","has_multiple_zip_codes":"0","needs_koaza":"0","has_chome":"0","shares_zip_code":"0","update_status":"0","change_reason":"0"},{"code":"22210","old_zip_code":"417  ","zip_code":"4170042","prefecture_kana":"ｼｽﾞｵｶｹﾝ","city_kana":"ﾌｼﾞｼ","town_kana":"ｱﾗﾀｼﾞﾏ","prefecture":"静岡県","city":"富士市","town":"荒田島","has_multiple_zip_codes":"0","needs_koaza":"0","has_chome":"0","shares_zip_code":"0","update_status":"0","change_reason":"0"},{"code":"22210","old_zip_code":"417  ","zip_code":"4170043","prefecture_kana":"ｼｽﾞｵｶｹﾝ","city_kana":"ﾌｼﾞｼ","town_kana":"ｱﾗﾀｼﾞﾏﾁｮｳ","prefecture":"静岡県","city":"富士市","town":"荒田島町","has_multiple_zip_codes":"0","needs_koaza":"0","has_chome":"0","shares_zip_code":"0","update_status":"0","change_reason":"0"},{"code":"22210","old_zip_code":"417  ","zip_code":"4170804","prefecture_kana":"ｼｽﾞｵｶｹﾝ","city_kana":"ﾌｼﾞｼ","town_kana":"ｲｼｲ","prefecture":"静岡県","city":"富士市","town":"石井","has_multiple_zip_codes":"0","needs_koaza":"0","has_chome":"0","shares_zip_code":"0","update_status":"0","change_reason":"0"},{"code":"22210","old_zip_code":"417  ","zip_code":"4170862","prefecture_kana":"ｼｽﾞｵｶｹﾝ","city_kana":"ﾌｼﾞｼ","town_kana":"ｲｼｻﾞｶ","prefecture":"静岡県","city":"富士市","town":"石坂","has_multiple_zip_codes":"0","needs_koaza":"0","has_chome":"0","shares_zip_code":"0","update_status":"0","change_reason":"0"},{"code":"22210","old_zip_code":"417  ","zip_code":"4170808","prefecture_kana":"ｼｽﾞｵｶｹﾝ","city_kana":"ﾌｼﾞｼ","town_kana":"ｲｯｼｷ","prefecture":"静岡県","city":"富士市","town":"一色","has_multiple_zip_codes":"0","needs_koaza":"0","has_chome":"0","shares_zip_code":"0","update_status":"0","change_reason":"0"},{"code":"22210","old_zip_code":"417  ","zip_code":"4170846","prefecture_kana":"ｼｽﾞｵｶｹﾝ","city_kana":"ﾌｼﾞｼ","town_kana":"ｲﾏｲ","prefecture":"静岡県","city":"富士市","town":"今井","has_multiple_zip_codes":"0","needs_koaza":"0","has_chome":"1","shares_zip_code":"0","update_status":"0","change_reason":"0"},{"code":"22210","old_zip_code":"417  ","zip_code":"4170001","prefecture_kana":"ｼｽﾞｵｶｹﾝ","city_kana":"ﾌｼﾞｼ","town_kana":"ｲﾏｲｽﾞﾐ","prefecture":"静岡県","city":"富士市","town":"今泉","has_multiple_zip_codes":"0","needs_koaza":"0","has_chome":"1","shares_zip_code":"0","update_status":"0","change_reason":"0"},{"code":"22210","old_zip_code":"417  ","zip_code":"4170802","prefecture_kana":"ｼｽﾞｵｶｹﾝ","city_kana":"ﾌｼﾞｼ","town_kana":"ｲﾏﾐﾔ","prefecture":"静岡県","city":"富士市","town":"今宮","has_multiple_zip_codes":"0","needs_koaza":"0","has_chome":"0","shares_zip_code":"0","update_status":"0","change_reason":"0"},{"code":"22210","old_zip_code":"417  ","zip_code":"4170853","prefecture_kana":"ｼｽﾞｵｶｹﾝ","city_kana":"ﾌｼﾞｼ","town_kana":"ｳﾄｶﾞﾜﾋｶﾞｼﾁｮｳ","prefecture":"静岡県","city":"富士市","town":"宇東川東町","has_multiple_zip_codes":"0","needs_koaza":"0","has_chome":"0","shares_zip_code":"0","update_status":"0","change_reason":"0"},{"code":"22210","old_zip_code":"417  ","zip_code":"4170854","prefecture_kana":"ｼｽﾞｵｶｹﾝ","city_kana":"ﾌｼﾞｼ","town_kana":"ｳﾄｶﾞﾜﾆｼﾁｮｳ","prefecture":"静岡県","city":"富士市","town":"宇東川西町","has_multiple_zip_codes":"0","needs_koaza":"0","has_chome":"0","shares_zip_code":"0","update_status":"0","change_reason":"0"},{"code":"22210","old_zip_code":"417  ","zip_code":"4170805","prefecture_kana":"ｼｽﾞｵｶｹﾝ","city_kana":"ﾌｼﾞｼ","town_kana":"ｳﾅｲｶﾞﾌﾁ","prefecture":"静岡県","city":"富士市","town":"鵜無ケ淵","has_multiple_zip_codes":"0","needs_koaza":"0","has_chome":"0","shares_zip_code":"0","update_status":"0","change_reason":"0"},{"code":"22210","old_zip_code":"417  ","zip_code":"4170025","prefecture_kana":"ｼｽﾞｵｶｹﾝ","city_kana":"ﾌｼﾞｼ","town_kana":"ｳﾘｼﾞﾏ","prefecture":"静岡県","city":"富士市","town":"瓜島","has_multiple_zip_codes":"0","needs_koaza":"0","has_chome":"0","shares_zip_code":"0","update_status":"0","change_reason":"0"},{"code":"22210","old_zip_code":"417  ","zip_code":"4170057","prefecture_kana":"ｼｽﾞｵｶｹﾝ","city_kana":"ﾌｼﾞｼ","town_kana":"ｳﾘｼﾞﾏﾁｮｳ","prefecture":"静岡県","city":"富士市","town":"瓜島町","has_multiple_zip_codes":"0","needs_koaza":"0","has_chome":"0","shares_zip_code":"0","update_status":"0","change_reason":"0"},{"code":"22210","old_zip_code":"417  ","zip_code":"4170811","prefecture_kana":"ｼｽﾞｵｶｹﾝ","city_kana":"ﾌｼﾞｼ","town_kana":"ｴﾉｵ","prefecture":"静岡県","city":"富士市","town":"江尾","has_multiple_zip_codes":"0","needs_koaza":"0","has_chome":"0","shares_zip_code":"0","update_status":"0","change_reason":"0"},{"code":"22210","old_zip_code":"417  ","zip_code":"4170817","prefecture_kana":"ｼｽﾞｵｶｹﾝ","city_kana":"ﾌｼﾞｼ","town_kana":"ｴﾉｵﾐﾅﾐ","prefecture":"静岡県","city":"富士市","town":"江尾南","has_multiple_zip_codes":"0","needs_koaza":"0","has_chome":"0","shares_zip_code":"0","update_status":"0","change_reason":"0"},{"code":"22210","old_zip_code":"417  ","zip_code":"4170848","prefecture_kana":"ｼｽﾞｵｶｹﾝ","city_kana":"ﾌｼﾞｼ","town_kana":"ｵｵﾉ","prefecture":"静岡県","city":"富士市","town":"大野","has_multiple_zip_codes":"0","needs_koaza":"0","has_chome":"0","shares_zip_code":"0","update_status":"0","change_reason":"0"},{"code":"22210","old_zip_code":"417  ","zip_code":"4170845","prefecture_kana":"ｼｽﾞｵｶｹﾝ","city_kana":"ﾌｼﾞｼ","town_kana":"ｵｵﾉｼﾝﾃﾞﾝ","prefecture":"静岡県","city":"富士市","town":"大野新田","has_multiple_zip_codes":"0","needs_koaza":"0","has_chome":"0","shares_zip_code":"0","update_status":"0","change_reason":"0"},{"code":"22210","old_zip_code":"417  ","zip_code":"4170801","prefecture_kana":"ｼｽﾞｵｶｹﾝ","city_kana":"ﾌｼﾞｼ","town_kana":"ｵｵﾌﾞﾁ","prefecture":"静岡県","city":"富士市","town":"大淵","has_multiple_zip_codes":"0","needs_koaza":"0","has_chome":"0","shares_zip_code":"0","update_status":"0","change_reason":"0"},{"code":"22210","old_zip_code":"417  ","zip_code":"4170803","prefecture_kana":"ｼｽﾞｵｶｹﾝ","city_kana":"ﾌｼﾞｼ","town_kana":"ｶｻﾞｷ","prefecture":"静岡県","city":"富士市","town":"桑崎","has_multiple_zip_codes":"0","needs_koaza":"0","has_chome":"0","shares_zip_code":"0","update_status":"0","change_reason":"0"},{"code":"22210","old_zip_code":"417  ","zip_code":"4170835","prefecture_kana":"ｼｽﾞｵｶｹﾝ","city_kana":"ﾌｼﾞｼ","town_kana":"ｶｼﾜﾊﾞﾗ","prefecture":"静岡県","city":"富士市","town":"柏原","has_multiple_zip_codes":"0","needs_koaza":"0","has_chome":"0","shares_zip_code":"0","update_status":"0","change_reason":"0"},{"code":"22210","old_zip_code":"417  ","zip_code":"4170821","prefecture_kana":"ｼｽﾞｵｶｹﾝ","city_kana":"ﾌｼﾞｼ","town_kana":"ｶﾐﾔ","prefecture":"静岡県","city":"富士市","town":"神谷","has_multiple_zip_codes":"0","needs_koaza":"0","has_chome":"0","shares_zip_code":"0","update_status":"0","change_reason":"0"},{"code":"22210","old_zip_code":"417  ","zip_code":"4170822","prefecture_kana":"ｼｽﾞｵｶｹﾝ","city_kana":"ﾌｼﾞｼ","town_kana":"ｶﾐﾔｼﾝﾏﾁ","prefecture":"静岡県","city":"富士市","town":"神谷新町","has_multiple_zip_codes":"0","needs_koaza":"0","has_chome":"0","shares_zip_code":"0","update_status":"0","change_reason":"0"},{"code":"22210","old_zip_code":"417  ","zip_code":"4170823","prefecture_kana":"ｼｽﾞｵｶｹﾝ","city_kana":"ﾌｼﾞｼ","town_kana":"ｶﾐﾔﾐﾅﾐ","prefecture":"静岡県","city":"富士市","town":"神谷南","has_multiple_zip_codes":"0","needs_koaza":"0","has_chome":"0","shares_zip_code":"0","update_status":"0","change_reason":"0"},{"code":"22210","old_zip_code":"417  ","zip_code":"4170825","prefecture_kana":"ｼｽﾞｵｶｹﾝ","city_kana":"ﾌｼﾞｼ","town_kana":"ｶﾜｼﾘ","prefecture":"静岡県","city":"富士市","town":"川尻","has_multiple_zip_codes":"0","needs_koaza":"0","has_chome":"0","shares_zip_code":"0","update_status":"0","change_reason":"0"},{"code":"22210","old_zip_code":"417  ","zip_code":"4170824","prefecture_kana":"ｼｽﾞｵｶｹﾝ","city_kana":"ﾌｼﾞｼ","town_kana":"ｶﾜｼﾘﾋｶﾞｼ","prefecture":"静岡県","city":"富士市","town":"川尻東","has_multiple_zip_codes":"0","needs_koaza":"0","has_chome":"0","shares_zip_code":"0","update_status":"0","change_reason":"0"},{"code":"22210","old_zip_code":"417  ","zip_code":"4170071","prefecture_kana":"ｼｽﾞｵｶｹﾝ","city_kana":"ﾌｼﾞｼ","town_kana":"ｸﾆｸﾎﾞ","prefecture":"静岡県","city":"富士市","town":"国久保","has_multiple_zip_codes":"0","needs_koaza":"0","has_chome":"1","shares_zip_code":"0","update_status":"0","change_reason":"0"},{"code":"22210","old_zip_code":"417  ","zip_code":"4170062","prefecture_kana":"ｼｽﾞｵｶｹﾝ","city_kana":"ﾌｼﾞｼ","town_kana":"ｺｳｻｲ","prefecture":"静岡県","city":"富士市","town":"香西","has_multiple_zip_codes":"0","needs_koaza":"0","has_chome":"0","shares_zip_code":"0","update_status":"0","change_reason":"0"},{"code":"22210","old_zip_code":"417  ","zip_code":"4170063","prefecture_kana":"ｼｽﾞｵｶｹﾝ","city_kana":"ﾌｼﾞｼ","town_kana":"ｺｳｻｲｼﾝﾃﾞﾝ","prefecture":"静岡県","city":"富士市","town":"香西新田","has_multiple_zip_codes":"0","needs_koaza":"0","has_chome":"0","shares_zip_code":"0","update_status":"0","change_reason":"0"},{"code":"22210","old_zip_code":"417  ","zip_code":"4170807","prefecture_kana":"ｼｽﾞｵｶｹﾝ","city_kana":"ﾌｼﾞｼ","town_kana":"ｺﾞｳﾄﾞ","prefecture":"静岡県","city":"富士市","town":"神戸","has_multiple_zip_codes":"0","needs_koaza":"0","has_chome":"0","shares_zip_code":"0","update_status":"0","change_reason":"0"},{"code":"22210","old_zip_code":"417  ","zip_code":"4170812","prefecture_kana":"ｼｽﾞｵｶｹﾝ","city_kana":"ﾌｼﾞｼ","town_kana":"ｻｶｲ","prefecture":"静岡県","city":"富士市","town":"境","has_multiple_zip_codes":"0","needs_koaza":"0","has_chome":"0","shares_zip_code":"0","update_status":"0","change_reason":"0"},{"code":"22210","old_zip_code":"417  ","zip_code":"4170842","prefecture_kana":"ｼｽﾞｵｶｹﾝ","city_kana":"ﾌｼﾞｼ","town_kana":"ｻﾝｼﾝﾃﾞﾝ","prefecture":"静岡県","city":"富士市","town":"三新田","has_multiple_zip_codes":"0","needs_koaza":"0","has_chome":"0","shares_zip_code":"0","update_status":"0","change_reason":"0"},{"code":"22210","old_zip_code":"417  ","zip_code":"4170856","prefecture_kana":"ｼｽﾞｵｶｹﾝ","city_kana":"ﾌｼﾞｼ","town_kana":"ｻﾝﾄﾞﾏｷ","prefecture":"静岡県","city":"富士市","town":"さんどまき","has_multiple_zip_codes":"0","needs_koaza":"0","has_chome":"0","shares_zip_code":"0","update_status":"0","change_reason":"0"},{"code":"22210","old_zip_code":"417  ","zip_code":"4170033","prefecture_kana":"ｼｽﾞｵｶｹﾝ","city_kana":"ﾌｼﾞｼ","town_kana":"ｼﾏﾀﾞﾁｮｳ","prefecture":"静岡県","city":"富士市","town":"島田町","has_multiple_zip_codes":"0","needs_koaza":"0","has_chome":"1","shares_zip_code":"0","update_status":"0","change_reason":"0"},{"code":"22210","old_zip_code":"417  ","zip_code":"4170004","prefecture_kana":"ｼｽﾞｵｶｹﾝ","city_kana":"ﾌｼﾞｼ","town_kana":"ｼﾝﾊﾞｼﾁｮｳ","prefecture":"静岡県","city":"富士市","town":"新橋町","has_multiple_zip_codes":"0","needs_koaza":"0","has_chome":"0","shares_zip_code":"0","update_status":"0","change_reason":"0"},{"code":"22210","old_zip_code":"417  ","zip_code":"4170015","prefecture_kana":"ｼｽﾞｵｶｹﾝ","city_kana":"ﾌｼﾞｼ","town_kana":"ｽｽﾞｶﾜﾁｮｳ","prefecture":"静岡県","city":"富士市","town":"鈴川町","has_multiple_zip_codes":"0","needs_koaza":"0","has_chome":"0","shares_zip_code":"0","update_status":"0","change_reason":"0"},{"code":"22210","old_zip_code":"417  ","zip_code":"4170013","prefecture_kana":"ｼｽﾞｵｶｹﾝ","city_kana":"ﾌｼﾞｼ","town_kana":"ｽｽﾞｶﾜﾅｶﾁｮｳ","prefecture":"静岡県","city":"富士市","town":"鈴川中町","has_multiple_zip_codes":"0","needs_koaza":"0","has_chome":"0","shares_zip_code":"0","update_status":"0","change_reason":"0"},{"code":"22210","old_zip_code":"417  ","zip_code":"4170014","prefecture_kana":"ｼｽﾞｵｶｹﾝ","city_kana":"ﾌｼﾞｼ","town_kana":"ｽｽﾞｶﾜﾆｼﾁｮｳ","prefecture":"静岡県","city":"富士市","town":"鈴川西町","has_multiple_zip_codes":"0","needs_koaza":"0","has_chome":"0","shares_zip_code":"0","update_status":"0","change_reason":"0"},{"code":"22210","old_zip_code":"417  ","zip_code":"4170012","prefecture_kana":"ｼｽﾞｵｶｹﾝ","city_kana":"ﾌｼﾞｼ","town_kana":"ｽｽﾞｶﾜﾋｶﾞｼﾁｮｳ","prefecture":"静岡県","city":"富士市","town":"鈴川東町","has_multiple_zip_codes":"0","needs_koaza":"0","has_chome":"0","shares_zip_code":"0","update_status":"0","change_reason":"0"},{"code":"22210","old_zip_code":"417  ","zip_code":"4170011","prefecture_kana":"ｼｽﾞｵｶｹﾝ","city_kana":"ﾌｼﾞｼ","town_kana":"ｽｽﾞｶﾜﾎﾝﾁｮｳ","prefecture":"静岡県","city":"富士市","town":"鈴川本町","has_multiple_zip_codes":"0","needs_koaza":"0","has_chome":"0","shares_zip_code":"0","update_status":"0","change_reason":"0"},{"code":"22210","old_zip_code":"417  ","zip_code":"4170072","prefecture_kana":"ｼｽﾞｵｶｹﾝ","city_kana":"ﾌｼﾞｼ","town_kana":"ｾﾝｹﾞﾝｶﾐﾁｮｳ","prefecture":"静岡県","city":"富士市","town":"浅間上町","has_multiple_zip_codes":"0","needs_koaza":"0","has_chome":"0","shares_zip_code":"0","update_status":"0","change_reason":"0"},{"code":"22210","old_zip_code":"417  ","zip_code":"4170073","prefecture_kana":"ｼｽﾞｵｶｹﾝ","city_kana":"ﾌｼﾞｼ","town_kana":"ｾﾝｹﾞﾝﾎﾝﾁｮｳ","prefecture":"静岡県","city":"富士市","town":"浅間本町","has_multiple_zip_codes":"0","needs_koaza":"0","has_chome":"0","shares_zip_code":"0","update_status":"0","change_reason":"0"},{"code":"22210","old_zip_code":"417  ","zip_code":"4170048","prefecture_kana":"ｼｽﾞｵｶｹﾝ","city_kana":"ﾌｼﾞｼ","town_kana":"ﾀｶｼﾏﾁｮｳ","prefecture":"静岡県","city":"富士市","town":"高島町","has_multiple_zip_codes":"0","needs_koaza":"0","has_chome":"0","shares_zip_code":"0","update_status":"0","change_reason":"0"},{"code":"22210","old_zip_code":"417  ","zip_code":"4170044","prefecture_kana":"ｼｽﾞｵｶｹﾝ","city_kana":"ﾌｼﾞｼ","town_kana":"ﾀｶﾈﾁｮｳ","prefecture":"静岡県","city":"富士市","town":"高嶺町","has_multiple_zip_codes":"0","needs_koaza":"0","has_chome":"0","shares_zip_code":"0","update_status":"0","change_reason":"0"},{"code":"22210","old_zip_code":"417  ","zip_code":"4170031","prefecture_kana":"ｼｽﾞｵｶｹﾝ","city_kana":"ﾌｼﾞｼ","town_kana":"ﾀｼﾞﾏ","prefecture":"静岡県","city":"富士市","town":"田島","has_multiple_zip_codes":"0","needs_koaza":"0","has_chome":"0","shares_zip_code":"0","update_status":"0","change_reason":"0"},{"code":"22210","old_zip_code":"417  ","zip_code":"4170032","prefecture_kana":"ｼｽﾞｵｶｹﾝ","city_kana":"ﾌｼﾞｼ","town_kana":"ﾀｼﾞﾏｼﾝﾃﾞﾝ","prefecture":"静岡県","city":"富士市","town":"田島新田","has_multiple_zip_codes":"0","needs_koaza":"0","has_chome":"0","shares_zip_code":"0","update_status":"0","change_reason":"0"},{"code":"22210","old_zip_code":"417  ","zip_code":"4170843","prefecture_kana":"ｼｽﾞｵｶｹﾝ","city_kana":"ﾌｼﾞｼ","town_kana":"ﾀﾅｶｼﾝﾃﾞﾝ","prefecture":"静岡県","city":"富士市","town":"田中新田","has_multiple_zip_codes":"0","needs_koaza":"0","has_chome":"0","shares_zip_code":"0","update_status":"0","change_reason":"0"},{"code":"22210","old_zip_code":"417  ","zip_code":"4170052","prefecture_kana":"ｼｽﾞｵｶｹﾝ","city_kana":"ﾌｼﾞｼ","town_kana":"ﾁｭｳｵｳﾁｮｳ","prefecture":"静岡県","city":"富士市","town":"中央町","has_multiple_zip_codes":"0","needs_koaza":"0","has_chome":"1","shares_zip_code":"0","update_status":"0","change_reason":"0"},{"code":"22210","old_zip_code":"417  ","zip_code":"4170034","prefecture_kana":"ｼｽﾞｵｶｹﾝ","city_kana":"ﾌｼﾞｼ","town_kana":"ﾂﾀ","prefecture":"静岡県","city":"富士市","town":"津田","has_multiple_zip_codes":"0","needs_koaza":"0","has_chome":"0","shares_zip_code":"0","update_status":"0","change_reason":"0"},{"code":"22210","old_zip_code":"417  ","zip_code":"4170035","prefecture_kana":"ｼｽﾞｵｶｹﾝ","city_kana":"ﾌｼﾞｼ","town_kana":"ﾂﾀﾁｮｳ","prefecture":"静岡県","city":"富士市","town":"津田町","has_multiple_zip_codes":"0","needs_koaza":"0","has_chome":"0","shares_zip_code":"0","update_status":"0","change_reason":"0"},{"code":"22210","old_zip_code":"417  ","zip_code":"4170061","prefecture_kana":"ｼｽﾞｵｶｹﾝ","city_kana":"ﾌｼﾞｼ","town_kana":"ﾃﾞﾝﾎﾞｳ","prefecture":"静岡県","city":"富士市","town":"伝法","has_multiple_zip_codes":"0","needs_koaza":"0","has_chome":"0","shares_zip_code":"0","update_status":"0","change_reason":"0"},{"code":"22210","old_zip_code":"417  ","zip_code":"4170037","prefecture_kana":"ｼｽﾞｵｶｹﾝ","city_kana":"ﾌｼﾞｼ","town_kana":"ﾄﾉｷ","prefecture":"静岡県","city":"富士市","town":"外木","has_multiple_zip_codes":"0","needs_koaza":"0","has_chome":"0","shares_zip_code":"0","update_status":"0","change_reason":"0"},{"code":"22210","old_zip_code":"417  ","zip_code":"4170832","prefecture_kana":"ｼｽﾞｵｶｹﾝ","city_kana":"ﾌｼﾞｼ","town_kana":"ﾅｶｶｼﾜﾊﾞﾗｼﾝﾃﾞﾝ","prefecture":"静岡県","city":"富士市","town":"中柏原新田","has_multiple_zip_codes":"0","needs_koaza":"0","has_chome":"0","shares_zip_code":"0","update_status":"0","change_reason":"0"},{"code":"22210","old_zip_code":"417  ","zip_code":"4170036","prefecture_kana":"ｼｽﾞｵｶｹﾝ","city_kana":"ﾌｼﾞｼ","town_kana":"ﾅｶｶﾜﾊﾗ(66､88､93､197､292-4､315ﾊﾞﾝﾁ)","prefecture":"静岡県","city":"富士市","town":"中河原（６６、８８、９３、１９７、２９２－４、３１５番地）","has_multiple_zip_codes":"1","needs_koaza":"0","has_chome":"0","shares_zip_code":"0","update_status":"0","change_reason":"0"},{"code":"22210","old_zip_code":"417  ","zip_code":"4170826","prefecture_kana":"ｼｽﾞｵｶｹﾝ","city_kana":"ﾌｼﾞｼ","town_kana":"ﾅｶｻﾞﾄ","prefecture":"静岡県","city":"富士市","town":"中里","has_multiple_zip_codes":"0","needs_koaza":"0","has_chome":"0","shares_zip_code":"0","update_status":"0","change_reason":"0"},{"code":"22210","old_zip_code":"417  ","zip_code":"4170809","prefecture_kana":"ｼｽﾞｵｶｹﾝ","city_kana":"ﾌｼﾞｼ","town_kana":"ﾅｶﾉ","prefecture":"静岡県","city":"富士市","town":"中野","has_multiple_zip_codes":"0","needs_koaza":"0","has_chome":"0","shares_zip_code":"0","update_status":"0","change_reason":"0"},{"code":"22210","old_zip_code":"417  ","zip_code":"4170054","prefecture_kana":"ｼｽﾞｵｶｹﾝ","city_kana":"ﾌｼﾞｼ","town_kana":"ﾅｶﾞﾀ","prefecture":"静岡県","city":"富士市","town":"永田","has_multiple_zip_codes":"0","needs_koaza":"0","has_chome":"0","shares_zip_code":"0","update_status":"0","change_reason":"0"},{"code":"22210","old_zip_code":"417  ","zip_code":"4170058","prefecture_kana":"ｼｽﾞｵｶｹﾝ","city_kana":"ﾌｼﾞｼ","town_kana":"ﾅｶﾞﾀｷﾀﾁｮｳ","prefecture":"静岡県","city":"富士市","town":"永田北町","has_multiple_zip_codes":"0","needs_koaza":"0","has_chome":"0","shares_zip_code":"0","update_status":"0","change_reason":"0"},{"code":"22210","old_zip_code":"417  ","zip_code":"4170055","prefecture_kana":"ｼｽﾞｵｶｹﾝ","city_kana":"ﾌｼﾞｼ","town_kana":"ﾅｶﾞﾀﾁｮｳ","prefecture":"静岡県","city":"富士市","town":"永田町","has_multiple_zip_codes":"0","needs_koaza":"0","has_chome":"1","shares_zip_code":"0","update_status":"0","change_reason":"0"},{"code":"22210","old_zip_code":"417  ","zip_code":"4170834","prefecture_kana":"ｼｽﾞｵｶｹﾝ","city_kana":"ﾌｼﾞｼ","town_kana":"ﾆｼｶｼﾜﾊﾞﾗｼﾝﾃﾞﾝ","prefecture":"静岡県","city":"富士市","town":"西柏原新田","has_multiple_zip_codes":"0","needs_koaza":"0","has_chome":"0","shares_zip_code":"0","update_status":"0","change_reason":"0"},{"code":"22210","old_zip_code":"417  ","zip_code":"4170045","prefecture_kana":"ｼｽﾞｵｶｹﾝ","city_kana":"ﾌｼﾞｼ","town_kana":"ﾆｼｷﾁｮｳ","prefecture":"静岡県","city":"富士市","town":"錦町","has_multiple_zip_codes":"0","needs_koaza":"0","has_chome":"1","shares_zip_code":"0","update_status":"0","change_reason":"0"},{"code":"22210","old_zip_code":"417  ","zip_code":"4170814","prefecture_kana":"ｼｽﾞｵｶｹﾝ","city_kana":"ﾌｼﾞｼ","town_kana":"ﾆｼﾌﾅﾂ","prefecture":"静岡県","city":"富士市","town":"西船津","has_multiple_zip_codes":"0","needs_koaza":"0","has_chome":"0","shares_zip_code":"0","update_status":"0","change_reason":"0"},{"code":"22210","old_zip_code":"417  ","zip_code":"4170833","prefecture_kana":"ｼｽﾞｵｶｹﾝ","city_kana":"ﾌｼﾞｼ","town_kana":"ﾇﾏﾀｼﾝﾃﾞﾝ","prefecture":"静岡県","city":"富士市","town":"沼田新田","has_multiple_zip_codes":"0","needs_koaza":"0","has_chome":"0","shares_zip_code":"0","update_status":"0","change_reason":"0"},{"code":"22210","old_zip_code":"417  ","zip_code":"4170852","prefecture_kana":"ｼｽﾞｵｶｹﾝ","city_kana":"ﾌｼﾞｼ","town_kana":"ﾊﾗﾀﾞ","prefecture":"静岡県","city":"富士市","town":"原田","has_multiple_zip_codes":"0","needs_koaza":"0","has_chome":"0","shares_zip_code":"0","update_status":"0","change_reason":"0"},{"code":"22210","old_zip_code":"417  ","zip_code":"4170831","prefecture_kana":"ｼｽﾞｵｶｹﾝ","city_kana":"ﾌｼﾞｼ","town_kana":"ﾋｶﾞｼｶｼﾜﾊﾞﾗｼﾝﾃﾞﾝ","prefecture":"静岡県","city":"富士市","town":"東柏原新田","has_multiple_zip_codes":"0","needs_koaza":"0","has_chome":"0","shares_zip_code":"0","update_status":"0","change_reason":"0"},{"code":"22210","old_zip_code":"417  ","zip_code":"4170847","prefecture_kana":"ｼｽﾞｵｶｹﾝ","city_kana":"ﾌｼﾞｼ","town_kana":"ﾋﾅ","prefecture":"静岡県","city":"富士市","town":"比奈","has_multiple_zip_codes":"0","needs_koaza":"0","has_chome":"0","shares_zip_code":"0","update_status":"0","change_reason":"0"},{"code":"22210","old_zip_code":"417  ","zip_code":"4170844","prefecture_kana":"ｼｽﾞｵｶｹﾝ","city_kana":"ﾌｼﾞｼ","town_kana":"ﾋﾉｷｼﾝﾃﾞﾝ","prefecture":"静岡県","city":"富士市","town":"檜新田","has_multiple_zip_codes":"0","needs_koaza":"0","has_chome":"0","shares_zip_code":"0","update_status":"0","change_reason":"0"},{"code":"22210","old_zip_code":"417  ","zip_code":"4170056","prefecture_kana":"ｼｽﾞｵｶｹﾝ","city_kana":"ﾌｼﾞｼ","town_kana":"ﾋﾉﾃﾞﾁｮｳ","prefecture":"静岡県","city":"富士市","town":"日乃出町","has_multiple_zip_codes":"0","needs_koaza":"0","has_chome":"0","shares_zip_code":"0","update_status":"0","change_reason":"0"},{"code":"22210","old_zip_code":"417  ","zip_code":"4170861","prefecture_kana":"ｼｽﾞｵｶｹﾝ","city_kana":"ﾌｼﾞｼ","town_kana":"ﾋﾛﾐﾋｶﾞｼﾎﾝﾁｮｳ","prefecture":"静岡県","city":"富士市","town":"広見東本町","has_multiple_zip_codes":"0","needs_koaza":"0","has_chome":"0","shares_zip_code":"0","update_status":"0","change_reason":"0"},{"code":"22210","old_zip_code":"417  ","zip_code":"4170863","prefecture_kana":"ｼｽﾞｵｶｹﾝ","city_kana":"ﾌｼﾞｼ","town_kana":"ﾋﾛﾐﾆｼﾎﾝﾁｮｳ","prefecture":"静岡県","city":"富士市","town":"広見西本町","has_multiple_zip_codes":"0","needs_koaza":"0","has_chome":"0","shares_zip_code":"0","update_status":"0","change_reason":"0"},{"code":"22210","old_zip_code":"417  ","zip_code":"4170864","prefecture_kana":"ｼｽﾞｵｶｹﾝ","city_kana":"ﾌｼﾞｼ","town_kana":"ﾋﾛﾐﾎﾝﾁｮｳ","prefecture":"静岡県","city":"富士市","town":"広見本町","has_multiple_zip_codes":"0","needs_koaza":"0","has_chome":"0","shares_zip_code":"0","update_status":"0","change_reason":"0"},{"code":"22210","old_zip_code":"417  ","zip_code":"4170841","prefecture_kana":"ｼｽﾞｵｶｹﾝ","city_kana":"ﾌｼﾞｼ","town_kana":"ﾌｼﾞｵｶ","prefecture":"静岡県","city":"富士市","town":"富士岡","has_multiple_zip_codes":"0","needs_koaza":"0","has_chome":"0","shares_zip_code":"0","update_status":"0","change_reason":"0"},{"code":"22210","old_zip_code":"417  ","zip_code":"4170851","prefecture_kana":"ｼｽﾞｵｶｹﾝ","city_kana":"ﾌｼﾞｼ","town_kana":"ﾌｼﾞﾐﾀﾞｲ","prefecture":"静岡県","city":"富士市","town":"富士見台","has_multiple_zip_codes":"0","needs_koaza":"0","has_chome":"1","shares_zip_code":"0","update_status":"0","change_reason":"0"},{"code":"22210","old_zip_code":"417  ","zip_code":"4170813","prefecture_kana":"ｼｽﾞｵｶｹﾝ","city_kana":"ﾌｼﾞｼ","town_kana":"ﾌﾅﾂ","prefecture":"静岡県","city":"富士市","town":"船津","has_multiple_zip_codes":"0","needs_koaza":"0","has_chome":"0","shares_zip_code":"0","update_status":"0","change_reason":"0"},{"code":"22210","old_zip_code":"417  ","zip_code":"4170806","prefecture_kana":"ｼｽﾞｵｶｹﾝ","city_kana":"ﾌｼﾞｼ","town_kana":"ﾏｶﾄﾞ","prefecture":"静岡県","city":"富士市","town":"間門","has_multiple_zip_codes":"0","needs_koaza":"0","has_chome":"0","shares_zip_code":"0","update_status":"0","change_reason":"0"},{"code":"22210","old_zip_code":"417  ","zip_code":"4170815","prefecture_kana":"ｼｽﾞｵｶｹﾝ","city_kana":"ﾌｼﾞｼ","town_kana":"ﾏｽｶﾞﾜ","prefecture":"静岡県","city":"富士市","town":"増川","has_multiple_zip_codes":"0","needs_koaza":"0","has_chome":"0","shares_zip_code":"0","update_status":"0","change_reason":"0"},{"code":"22210","old_zip_code":"417  ","zip_code":"4170816","prefecture_kana":"ｼｽﾞｵｶｹﾝ","city_kana":"ﾌｼﾞｼ","town_kana":"ﾏｽｶﾞﾜｼﾝﾏﾁ","prefecture":"静岡県","city":"富士市","town":"増川新町","has_multiple_zip_codes":"0","needs_koaza":"0","has_chome":"0","shares_zip_code":"0","update_status":"0","change_reason":"0"},{"code":"22210","old_zip_code":"417  ","zip_code":"4170855","prefecture_kana":"ｼｽﾞｵｶｹﾝ","city_kana":"ﾌｼﾞｼ","town_kana":"ﾐﾂｻﾞﾜ","prefecture":"静岡県","city":"富士市","town":"三ツ沢","has_multiple_zip_codes":"0","needs_koaza":"0","has_chome":"0","shares_zip_code":"0","update_status":"0","change_reason":"0"},{"code":"22210","old_zip_code":"417  ","zip_code":"4170049","prefecture_kana":"ｼｽﾞｵｶｹﾝ","city_kana":"ﾌｼﾞｼ","town_kana":"ﾐﾄﾞﾘﾁｮｳ","prefecture":"静岡県","city":"富士市","town":"緑町","has_multiple_zip_codes":"0","needs_koaza":"0","has_chome":"0","shares_zip_code":"0","update_status":"0","change_reason":"0"},{"code":"22210","old_zip_code":"417  ","zip_code":"4170026","prefecture_kana":"ｼｽﾞｵｶｹﾝ","city_kana":"ﾌｼﾞｼ","town_kana":"ﾐﾅﾐﾁｮｳ","prefecture":"静岡県","city":"富士市","town":"南町","has_multiple_zip_codes":"0","needs_koaza":"0","has_chome":"0","shares_zip_code":"0","update_status":"0","change_reason":"0"},{"code":"22210","old_zip_code":"417  ","zip_code":"4170041","prefecture_kana":"ｼｽﾞｵｶｹﾝ","city_kana":"ﾌｼﾞｼ","town_kana":"ﾐﾕｷﾁｮｳ","prefecture":"静岡県","city":"富士市","town":"御幸町","has_multiple_zip_codes":"0","needs_koaza":"0","has_chome":"0","shares_zip_code":"0","update_status":"0","change_reason":"0"},{"code":"22210","old_zip_code":"417  ","zip_code":"4170024","prefecture_kana":"ｼｽﾞｵｶｹﾝ","city_kana":"ﾌｼﾞｼ","town_kana":"ﾔｼﾛﾁｮｳ","prefecture":"静岡県","city":"富士市","town":"八代町","has_multiple_zip_codes":"0","needs_koaza":"0","has_chome":"0","shares_zip_code":"0","update_status":"0","change_reason":"0"},{"code":"22210","old_zip_code":"417  ","zip_code":"4170064","prefecture_kana":"ｼｽﾞｵｶｹﾝ","city_kana":"ﾌｼﾞｼ","town_kana":"ﾔﾖｲ","prefecture":"静岡県","city":"富士市","town":"弥生","has_multiple_zip_codes":"0","needs_koaza":"0","has_chome":"0","shares_zip_code":"0","update_status":"0","change_reason":"0"},{"code":"22210","old_zip_code":"417  ","zip_code":"4170065","prefecture_kana":"ｼｽﾞｵｶｹﾝ","city_kana":"ﾌｼﾞｼ","town_kana":"ﾔﾖｲｼﾝﾃﾞﾝ","prefecture":"静岡県","city":"富士市","town":"弥生新田","has_multiple_zip_codes":"0","needs_koaza":"0","has_chome":"0","shares_zip_code":"0","update_status":"0","change_reason":"0"},{"code":"22210","old_zip_code":"417  ","zip_code":"4170051","prefecture_kana":"ｼｽﾞｵｶｹﾝ","city_kana":"ﾌｼﾞｼ","town_kana":"ﾖｼﾜﾗ","prefecture":"静岡県","city":"富士市","town":"吉原","has_multiple_zip_codes":"0","needs_koaza":"0","has_chome":"1","shares_zip_code":"0","update_status":"0","change_reason":"0"},{"code":"22210","old_zip_code":"417  ","zip_code":"4170023","prefecture_kana":"ｼｽﾞｵｶｹﾝ","city_kana":"ﾌｼﾞｼ","town_kana":"ﾖｼﾜﾗﾀｶﾗﾁｮｳ","prefecture":"静岡県","city":"富士市","town":"吉原宝町","has_multiple_zip_codes":"0","needs_koaza":"0","has_chome":"0","shares_zip_code":"0","update_status":"0","change_reason":"0"},{"code":"22210","old_zip_code":"417  ","zip_code":"4170021","prefecture_kana":"ｼｽﾞｵｶｹﾝ","city_kana":"ﾌｼﾞｼ","town_kana":"ﾖﾀﾞﾊﾗ","prefecture":"静岡県","city":"富士市","town":"依田原","has_multiple_zip_codes":"0","needs_koaza":"0","has_chome":"0","shares_zip_code":"0","update_status":"0","change_reason":"0"},{"code":"22210","old_zip_code":"417  ","zip_code":"4170053","prefecture_kana":"ｼｽﾞｵｶｹﾝ","city_kana":"ﾌｼﾞｼ","town_kana":"ﾖﾀﾞﾊﾗｼﾝﾃﾞﾝ","prefecture":"静岡県","city":"富士市","town":"依田原新田","has_multiple_zip_codes":"0","needs_koaza":"0","has_chome":"0","shares_zip_code":"0","update_status":"0","change_reason":"0"},{"code":"22210","old_zip_code":"417  ","zip_code":"4170022","prefecture_kana":"ｼｽﾞｵｶｹﾝ","city_kana":"ﾌｼﾞｼ","town_kana":"ﾖﾀﾞﾊﾗﾁｮｳ","prefecture":"静岡県","city":"富士市","town":"依田原町","has_multiple_zip_codes":"0","needs_koaza":"0","has_chome":"0","shares_zip_code":"0","update_status":"0","change_reason":"0"},{"code":"22210","old_zip_code":"417  ","zip_code":"4170002","prefecture_kana":"ｼｽﾞｵｶｹﾝ","city_kana":"ﾌｼﾞｼ","town_kana":"ﾖﾀﾞﾊﾞｼ","prefecture":"静岡県","city":"富士市","town":"依田橋","has_multiple_zip_codes":"0","needs_koaza":"0","has_chome":"0","shares_zip_code":"0","update_status":"0","change_reason":"0"},{"code":"22210","old_zip_code":"417  ","zip_code":"4170003","prefecture_kana":"ｼｽﾞｵｶｹﾝ","city_kana":"ﾌｼﾞｼ","town_kana":"ﾖﾀﾞﾊﾞｼﾁｮｳ","prefecture":"静岡県","city":"富士市","town":"依田橋町","has_multiple_zip_codes":"0","needs_koaza":"0","has_chome":"0","shares_zip_code":"0","update_status":"0","change_reason":"0"}]