[{"code":"27116","old_zip_code":"544  ","zip_code":"5440000","prefecture_kana":"ｵｵｻｶﾌ","city_kana":"ｵｵｻｶｼｲｸﾉｸ","town_kana":"ｲｶﾆｹｲｻｲｶﾞﾅｲﾊﾞｱｲ","prefecture":"大阪府","city":"大阪市生野区","town":"以下に掲載がない場合","has_multiple_zip_codes":"0","needs_koaza":"0","has_chome":"0","shares_zip_code":"0","update_status":"0","change_reason":"0"},{"code":"27116","old_zip_code":"544  ","zip_code":"5440025","prefecture_kana":"ｵｵｻｶﾌ","city_kana":"ｵｵｻｶｼｲｸﾉｸ","town_kana":"ｲｸﾉﾋｶﾞｼ","prefecture":"大阪府","city":"大阪市生野区","town":"生野東","has_multiple_zip_codes":"0","needs_koaza":"0","has_chome":"1","shares_zip_code":"0","update_status":"0","change_reason":"0"},{"code":"27116","old_zip_code":"544  ","zip_code":"5440024","prefecture_kana":"ｵｵｻｶﾌ","city_kana":"ｵｵｻｶｼｲｸﾉｸ","town_kana":"ｲｸﾉﾆｼ","prefecture":"大阪府","city":"大阪市生野区","town":"生野西","has_multiple_zip_codes":"0","needs_koaza":"0","has_chome":"1","shares_zip_code":"0","update_status":"0","change_reason":"0"},{"code":"27116","old_zip_code":"544  ","zip_code":"5440021","prefecture_kana":"ｵｵｻｶﾌ","city_kana":"ｵｵｻｶｼｲｸﾉｸ","town_kana":"ｶﾂﾔﾏﾐﾅﾐ","prefecture":"大阪府","city":"大阪市生野区","town":"勝山南","has_multiple_zip_codes":"0","needs_koaza":"0","has_chome":"1","shares_zip_code":"0","update_status":"0","change_reason":"0"},{"code":"27116","old_zip_code":"544  ","zip_code":"5440033","prefecture_kana":"ｵｵｻｶﾌ","city_kana":"ｵｵｻｶｼｲｸﾉｸ","town_kana":"ｶﾂﾔﾏｷﾀ","prefecture":"大阪府","city":"大阪市生野区","town":"勝山北","has_multiple_zip_codes":"0","needs_koaza":"0","has_chome":"1","shares_zip_code":"0","update_status":"0","change_reason":"0"},{"code":"27116","old_zip_code":"544  ","zip_code":"5440022","prefecture_kana":"ｵｵｻｶﾌ","city_kana":"ｵｵｻｶｼｲｸﾉｸ","town_kana":"ｼｬﾘｼﾞ","prefecture":"大阪府","city":"大阪市生野区","town":"舎利寺","has_multiple_zip_codes":"0","needs_koaza":"0","has_chome":"1","shares_zip_code":"0","update_status":"0","change_reason":"0"},{"code":"27116","old_zip_code":"544  ","zip_code":"5440002","prefecture_kana":"ｵｵｻｶﾌ","city_kana":"ｵｵｻｶｼｲｸﾉｸ","town_kana":"ｼｮｳｼﾞ","prefecture":"大阪府","city":"大阪市生野区","town":"小路","has_multiple_zip_codes":"0","needs_koaza":"0","has_chome":"1","shares_zip_code":"0","update_status":"0","change_reason":"0"},{"code":"27116","old_zip_code":"544  ","zip_code":"5440003","prefecture_kana":"ｵｵｻｶﾌ","city_kana":"ｵｵｻｶｼｲｸﾉｸ","town_kana":"ｼｮｳｼﾞﾋｶﾞｼ","prefecture":"大阪府","city":"大阪市生野区","town":"小路東","has_multiple_zip_codes":"0","needs_koaza":"0","has_chome":"1","shares_zip_code":"0","update_status":"0","change_reason":"0"},{"code":"27116","old_zip_code":"544  ","zip_code":"5440001","prefecture_kana":"ｵｵｻｶﾌ","city_kana":"ｵｵｻｶｼｲｸﾉｸ","town_kana":"ｼﾝｲﾏｻﾞﾄ","prefecture":"大阪府","city":"大阪市生野区","town":"新今里","has_multiple_zip_codes":"0","needs_koaza":"0","has_chome":"1","shares_zip_code":"0","update_status":"0","change_reason":"0"},{"code":"27116","old_zip_code":"544  ","zip_code":"5440011","prefecture_kana":"ｵｵｻｶﾌ","city_kana":"ｵｵｻｶｼｲｸﾉｸ","town_kana":"ﾀｼﾞﾏ","prefecture":"大阪府","city":"大阪市生野区","town":"田島","has_multiple_zip_codes":"0","needs_koaza":"0","has_chome":"1","shares_zip_code":"0","update_status":"0","change_reason":"0"},{"code":"27116","old_zip_code":"544  ","zip_code":"5440013","prefecture_kana":"ｵｵｻｶﾌ","city_kana":"ｵｵｻｶｼｲｸﾉｸ","town_kana":"ﾀﾂﾐﾅｶ","prefecture":"大阪府","city":"大阪市生野区","town":"巽中","has_multiple_zip_codes":"0","needs_koaza":"0","has_chome":"1","shares_zip_code":"0","update_status":"0","change_reason":"0"},{"code":"27116","old_zip_code":"544  ","zip_code":"5440014","prefecture_kana":"ｵｵｻｶﾌ","city_kana":"ｵｵｻｶｼｲｸﾉｸ","town_kana":"ﾀﾂﾐﾋｶﾞｼ","prefecture":"大阪府","city":"大阪市生野区","town":"巽東","has_multiple_zip_codes":"0","needs_koaza":"0","has_chome":"1","shares_zip_code":"0","update_status":"0","change_reason":"0"},{"code":"27116","old_zip_code":"544  ","zip_code":"5440012","prefecture_kana":"ｵｵｻｶﾌ","city_kana":"ｵｵｻｶｼｲｸﾉｸ","town_kana":"ﾀﾂﾐﾆｼ","prefecture":"大阪府","city":"大阪市生野区","town":"巽西","has_multiple_zip_codes":"0","needs_koaza":"0","has_chome":"1","shares_zip_code":"0","update_status":"0","change_reason":"0"},{"code":"27116","old_zip_code":"544  ","zip_code":"5440015","prefecture_kana":"ｵｵｻｶﾌ","city_kana":"ｵｵｻｶｼｲｸﾉｸ","town_kana":"ﾀﾂﾐﾐﾅﾐ","prefecture":"大阪府","city":"大阪市生野区","town":"巽南","has_multiple_zip_codes":"0","needs_koaza":"0","has_chome":"1","shares_zip_code":"0","update_status":"0","change_reason":"0"},{"code":"27116","old_zip_code":"544  ","zip_code":"5440004","prefecture_kana":"ｵｵｻｶﾌ","city_kana":"ｵｵｻｶｼｲｸﾉｸ","town_kana":"ﾀﾂﾐｷﾀ","prefecture":"大阪府","city":"大阪市生野区","town":"巽北","has_multiple_zip_codes":"0","needs_koaza":"0","has_chome":"1","shares_zip_code":"0","update_status":"0","change_reason":"0"},{"code":"27116","old_zip_code":"544  ","zip_code":"5440031","prefecture_kana":"ｵｵｻｶﾌ","city_kana":"ｵｵｻｶｼｲｸﾉｸ","town_kana":"ﾂﾙﾊｼ","prefecture":"大阪府","city":"大阪市生野区","town":"鶴橋","has_multiple_zip_codes":"0","needs_koaza":"0","has_chome":"1","shares_zip_code":"0","update_status":"0","change_reason":"0"},{"code":"27116","old_zip_code":"544  ","zip_code":"5440005","prefecture_kana":"ｵｵｻｶﾌ","city_kana":"ｵｵｻｶｼｲｸﾉｸ","town_kana":"ﾅｶｶﾞﾜ","prefecture":"大阪府","city":"大阪市生野区","town":"中川","has_multiple_zip_codes":"0","needs_koaza":"0","has_chome":"1","shares_zip_code":"0","update_status":"0","change_reason":"0"},{"code":"27116","old_zip_code":"544  ","zip_code":"5440006","prefecture_kana":"ｵｵｻｶﾌ","city_kana":"ｵｵｻｶｼｲｸﾉｸ","town_kana":"ﾅｶｶﾞﾜﾋｶﾞｼ","prefecture":"大阪府","city":"大阪市生野区","town":"中川東","has_multiple_zip_codes":"0","needs_koaza":"0","has_chome":"1","shares_zip_code":"0","update_status":"0","change_reason":"0"},{"code":"27116","old_zip_code":"544  ","zip_code":"5440032","prefecture_kana":"ｵｵｻｶﾌ","city_kana":"ｵｵｻｶｼｲｸﾉｸ","town_kana":"ﾅｶｶﾞﾜﾆｼ","prefecture":"大阪府","city":"大阪市生野区","town":"中川西","has_multiple_zip_codes":"0","needs_koaza":"0","has_chome":"1","shares_zip_code":"0","update_status":"0","change_reason":"0"},{"code":"27116","old_zip_code":"544  ","zip_code":"5440023","prefecture_kana":"ｵｵｻｶﾌ","city_kana":"ｵｵｻｶｼｲｸﾉｸ","town_kana":"ﾊﾔｼｼﾞ","prefecture":"大阪府","city":"大阪市生野区","town":"林寺","has_multiple_zip_codes":"0","needs_koaza":"0","has_chome":"1","shares_zip_code":"0","update_status":"0","change_reason":"0"},{"code":"27116","old_zip_code":"544  ","zip_code":"5440034","prefecture_kana":"ｵｵｻｶﾌ","city_kana":"ｵｵｻｶｼｲｸﾉｸ","town_kana":"ﾓﾓﾀﾞﾆ","prefecture":"大阪府","city":"大阪市生野区","town":"桃谷","has_multiple_zip_codes":"0","needs_koaza":"0","has_chome":"1","shares_zip_code":"0","update_status":"0","change_reason":"0"}]