[{"code":"46220","old_zip_code":"897  ","zip_code":"8970000","prefecture_kana":"ｶｺﾞｼﾏｹﾝ","city_kana":"ﾐﾅﾐｻﾂﾏｼ","town_kana":"ｲｶﾆｹｲｻｲｶﾞﾅｲﾊﾞｱｲ","prefecture":"鹿児島県","city":"南さつま市","town":"以下に掲載がない場合","has_multiple_zip_codes":"0","needs_koaza":"0","has_chome":"0","shares_zip_code":"0","update_status":"0","change_reason":"0"},{"code":"46220","old_zip_code":"89712","zip_code":"8971201","prefecture_kana":"ｶｺﾞｼﾏｹﾝ","city_kana":"ﾐﾅﾐｻﾂﾏｼ","town_kana":"ｵｵｳﾗﾁｮｳ(ｿﾉﾀ)","prefecture":"鹿児島県","city":"南さつま市","town":"大浦町（その他）","has_multiple_zip_codes":"1","needs_koaza":"0","has_chome":"0","shares_zip_code":"0","update_status":"0","change_reason":"0"},{"code":"46220","old_zip_code":"89713","zip_code":"8971302","prefecture_kana":"ｶｺﾞｼﾏｹﾝ","city_kana":"ﾐﾅﾐｻﾂﾏｼ","town_kana":"ｶｻｻﾁｮｳｱｺｳｷﾞ","prefecture":"鹿児島県","city":"南さつま市","town":"笠沙町赤生木","has_multiple_zip_codes":"0","needs_koaza":"0","has_chome":"0","shares_zip_code":"0","update_status":"0","change_reason":"0"},{"code":"46220","old_zip_code":"89713","zip_code":"8971301","prefecture_kana":"ｶｺﾞｼﾏｹﾝ","city_kana":"ﾐﾅﾐｻﾂﾏｼ","town_kana":"ｶｻｻﾁｮｳｶﾀｳﾗ","prefecture":"鹿児島県","city":"南さつま市","town":"笠沙町片浦","has_multiple_zip_codes":"0","needs_koaza":"0","has_chome":"0","shares_zip_code":"0","update_status":"0","change_reason":"0"},{"code":"46220","old_zip_code":"897  ","zip_code":"8970004","prefecture_kana":"ｶｺﾞｼﾏｹﾝ","city_kana":"ﾐﾅﾐｻﾂﾏｼ","town_kana":"ｶｾﾀﾞｳﾁﾔﾏﾀﾞ","prefecture":"鹿児島県","city":"南さつま市","town":"加世田内山田","has_multiple_zip_codes":"0","needs_koaza":"0","has_chome":"0","shares_zip_code":"0","update_status":"0","change_reason":"0"},{"code":"46220","old_zip_code":"897  ","zip_code":"8970003","prefecture_kana":"ｶｺﾞｼﾏｹﾝ","city_kana":"ﾐﾅﾐｻﾂﾏｼ","town_kana":"ｶｾﾀﾞｶﾜﾊﾞﾀ","prefecture":"鹿児島県","city":"南さつま市","town":"加世田川畑","has_multiple_zip_codes":"0","needs_koaza":"0","has_chome":"0","shares_zip_code":"0","update_status":"0","change_reason":"0"},{"code":"46220","old_zip_code":"89711","zip_code":"8971122","prefecture_kana":"ｶｺﾞｼﾏｹﾝ","city_kana":"ﾐﾅﾐｻﾂﾏｼ","town_kana":"ｶｾﾀﾞｺﾐﾅﾄ","prefecture":"鹿児島県","city":"南さつま市","town":"加世田小湊","has_multiple_zip_codes":"0","needs_koaza":"0","has_chome":"0","shares_zip_code":"0","update_status":"0","change_reason":"0"},{"code":"46220","old_zip_code":"897  ","zip_code":"8970008","prefecture_kana":"ｶｺﾞｼﾏｹﾝ","city_kana":"ﾐﾅﾐｻﾂﾏｼ","town_kana":"ｶｾﾀﾞｼﾞﾄｳｼｮ","prefecture":"鹿児島県","city":"南さつま市","town":"加世田地頭所","has_multiple_zip_codes":"0","needs_koaza":"0","has_chome":"0","shares_zip_code":"0","update_status":"0","change_reason":"0"},{"code":"46220","old_zip_code":"897  ","zip_code":"8970007","prefecture_kana":"ｶｺﾞｼﾏｹﾝ","city_kana":"ﾐﾅﾐｻﾂﾏｼ","town_kana":"ｶｾﾀﾞｼﾗｶﾒ","prefecture":"鹿児島県","city":"南さつま市","town":"加世田白亀","has_multiple_zip_codes":"0","needs_koaza":"0","has_chome":"0","shares_zip_code":"0","update_status":"0","change_reason":"0"},{"code":"46220","old_zip_code":"89711","zip_code":"8971123","prefecture_kana":"ｶｺﾞｼﾏｹﾝ","city_kana":"ﾐﾅﾐｻﾂﾏｼ","town_kana":"ｶｾﾀﾞﾀｶﾊｼ","prefecture":"鹿児島県","city":"南さつま市","town":"加世田高橋","has_multiple_zip_codes":"0","needs_koaza":"0","has_chome":"0","shares_zip_code":"0","update_status":"0","change_reason":"0"},{"code":"46220","old_zip_code":"897  ","zip_code":"8970002","prefecture_kana":"ｶｺﾞｼﾏｹﾝ","city_kana":"ﾐﾅﾐｻﾂﾏｼ","town_kana":"ｶｾﾀﾞﾀｹﾀﾞ","prefecture":"鹿児島県","city":"南さつま市","town":"加世田武田","has_multiple_zip_codes":"0","needs_koaza":"0","has_chome":"0","shares_zip_code":"0","update_status":"0","change_reason":"0"},{"code":"46220","old_zip_code":"89711","zip_code":"8971121","prefecture_kana":"ｶｺﾞｼﾏｹﾝ","city_kana":"ﾐﾅﾐｻﾂﾏｼ","town_kana":"ｶｾﾀﾞﾄｳｼﾞﾝﾊﾞﾗ","prefecture":"鹿児島県","city":"南さつま市","town":"加世田唐仁原","has_multiple_zip_codes":"0","needs_koaza":"0","has_chome":"0","shares_zip_code":"0","update_status":"0","change_reason":"0"},{"code":"46220","old_zip_code":"897  ","zip_code":"8970009","prefecture_kana":"ｶｺﾞｼﾏｹﾝ","city_kana":"ﾐﾅﾐｻﾂﾏｼ","town_kana":"ｶｾﾀﾞﾊｰﾓﾆｰ","prefecture":"鹿児島県","city":"南さつま市","town":"加世田ハーモニー","has_multiple_zip_codes":"0","needs_koaza":"0","has_chome":"0","shares_zip_code":"0","update_status":"0","change_reason":"0"},{"code":"46220","old_zip_code":"897  ","zip_code":"8970031","prefecture_kana":"ｶｺﾞｼﾏｹﾝ","city_kana":"ﾐﾅﾐｻﾂﾏｼ","town_kana":"ｶｾﾀﾞﾋｶﾞｼﾎﾝﾁｮｳ","prefecture":"鹿児島県","city":"南さつま市","town":"加世田東本町","has_multiple_zip_codes":"0","needs_koaza":"0","has_chome":"0","shares_zip_code":"0","update_status":"0","change_reason":"0"},{"code":"46220","old_zip_code":"897  ","zip_code":"8970005","prefecture_kana":"ｶｺﾞｼﾏｹﾝ","city_kana":"ﾐﾅﾐｻﾂﾏｼ","town_kana":"ｶｾﾀﾞﾌﾓﾄﾁｮｳ","prefecture":"鹿児島県","city":"南さつま市","town":"加世田麓町","has_multiple_zip_codes":"0","needs_koaza":"0","has_chome":"0","shares_zip_code":"0","update_status":"0","change_reason":"0"},{"code":"46220","old_zip_code":"897  ","zip_code":"8970006","prefecture_kana":"ｶｺﾞｼﾏｹﾝ","city_kana":"ﾐﾅﾐｻﾂﾏｼ","town_kana":"ｶｾﾀﾞﾎﾝﾁｮｳ","prefecture":"鹿児島県","city":"南さつま市","town":"加世田本町","has_multiple_zip_codes":"0","needs_koaza":"0","has_chome":"0","shares_zip_code":"0","update_status":"0","change_reason":"0"},{"code":"46220","old_zip_code":"89711","zip_code":"8971125","prefecture_kana":"ｶｺﾞｼﾏｹﾝ","city_kana":"ﾐﾅﾐｻﾂﾏｼ","town_kana":"ｶｾﾀﾞﾏｽﾔﾏ","prefecture":"鹿児島県","city":"南さつま市","town":"加世田益山","has_multiple_zip_codes":"0","needs_koaza":"0","has_chome":"0","shares_zip_code":"0","update_status":"0","change_reason":"0"},{"code":"46220","old_zip_code":"89711","zip_code":"8971124","prefecture_kana":"ｶｺﾞｼﾏｹﾝ","city_kana":"ﾐﾅﾐｻﾂﾏｼ","town_kana":"ｶｾﾀﾞﾐﾔﾊﾞﾗ","prefecture":"鹿児島県","city":"南さつま市","town":"加世田宮原","has_multiple_zip_codes":"0","needs_koaza":"0","has_chome":"0","shares_zip_code":"0","update_status":"0","change_reason":"0"},{"code":"46220","old_zip_code":"897  ","zip_code":"8970001","prefecture_kana":"ｶｺﾞｼﾏｹﾝ","city_kana":"ﾐﾅﾐｻﾂﾏｼ","town_kana":"ｶｾﾀﾞﾑﾗﾊﾗ","prefecture":"鹿児島県","city":"南さつま市","town":"加世田村原","has_multiple_zip_codes":"0","needs_koaza":"0","has_chome":"0","shares_zip_code":"0","update_status":"0","change_reason":"0"},{"code":"46223","old_zip_code":"89702","zip_code":"8970200","prefecture_kana":"ｶｺﾞｼﾏｹﾝ","city_kana":"ﾐﾅﾐｷｭｳｼｭｳｼ","town_kana":"ｲｶﾆｹｲｻｲｶﾞﾅｲﾊﾞｱｲ","prefecture":"鹿児島県","city":"南九州市","town":"以下に掲載がない場合","has_multiple_zip_codes":"0","needs_koaza":"0","has_chome":"0","shares_zip_code":"0","update_status":"0","change_reason":"0"},{"code":"46223","old_zip_code":"89702","zip_code":"8970212","prefecture_kana":"ｶｺﾞｼﾏｹﾝ","city_kana":"ﾐﾅﾐｷｭｳｼｭｳｼ","town_kana":"ｶﾜﾅﾍﾞﾁｮｳｲﾏﾀﾞ","prefecture":"鹿児島県","city":"南九州市","town":"川辺町今田","has_multiple_zip_codes":"0","needs_koaza":"0","has_chome":"0","shares_zip_code":"0","update_status":"0","change_reason":"0"},{"code":"46223","old_zip_code":"89702","zip_code":"8970213","prefecture_kana":"ｶｺﾞｼﾏｹﾝ","city_kana":"ﾐﾅﾐｷｭｳｼｭｳｼ","town_kana":"ｶﾜﾅﾍﾞﾁｮｳｵﾉ","prefecture":"鹿児島県","city":"南九州市","town":"川辺町小野","has_multiple_zip_codes":"0","needs_koaza":"0","has_chome":"0","shares_zip_code":"0","update_status":"0","change_reason":"0"},{"code":"46223","old_zip_code":"89701","zip_code":"8970131","prefecture_kana":"ｶｺﾞｼﾏｹﾝ","city_kana":"ﾐﾅﾐｷｭｳｼｭｳｼ","town_kana":"ｶﾜﾅﾍﾞﾁｮｳｶﾐﾔﾏﾀﾞ","prefecture":"鹿児島県","city":"南九州市","town":"川辺町上山田","has_multiple_zip_codes":"0","needs_koaza":"0","has_chome":"0","shares_zip_code":"0","update_status":"0","change_reason":"0"},{"code":"46223","old_zip_code":"89702","zip_code":"8970202","prefecture_kana":"ｶｺﾞｼﾏｹﾝ","city_kana":"ﾐﾅﾐｷｭｳｼｭｳｼ","town_kana":"ｶﾜﾅﾍﾞﾁｮｳｷﾖﾐｽﾞ","prefecture":"鹿児島県","city":"南九州市","town":"川辺町清水","has_multiple_zip_codes":"0","needs_koaza":"0","has_chome":"0","shares_zip_code":"0","update_status":"0","change_reason":"0"},{"code":"46223","old_zip_code":"89702","zip_code":"8970201","prefecture_kana":"ｶｺﾞｼﾏｹﾝ","city_kana":"ﾐﾅﾐｷｭｳｼｭｳｼ","town_kana":"ｶﾜﾅﾍﾞﾁｮｳｺｳﾄﾞﾉ","prefecture":"鹿児島県","city":"南九州市","town":"川辺町神殿","has_multiple_zip_codes":"0","needs_koaza":"0","has_chome":"0","shares_zip_code":"0","update_status":"0","change_reason":"0"},{"code":"46223","old_zip_code":"89701","zip_code":"8970133","prefecture_kana":"ｶｺﾞｼﾏｹﾝ","city_kana":"ﾐﾅﾐｷｭｳｼｭｳｼ","town_kana":"ｶﾜﾅﾍﾞﾁｮｳｼﾓﾔﾏﾀﾞ","prefecture":"鹿児島県","city":"南九州市","town":"川辺町下山田","has_multiple_zip_codes":"0","needs_koaza":"0","has_chome":"0","shares_zip_code":"0","update_status":"0","change_reason":"0"},{"code":"46223","old_zip_code":"89702","zip_code":"8970223","prefecture_kana":"ｶｺﾞｼﾏｹﾝ","city_kana":"ﾐﾅﾐｷｭｳｼｭｳｼ","town_kana":"ｶﾜﾅﾍﾞﾁｮｳﾀｶﾀ","prefecture":"鹿児島県","city":"南九州市","town":"川辺町高田","has_multiple_zip_codes":"0","needs_koaza":"0","has_chome":"0","shares_zip_code":"0","update_status":"0","change_reason":"0"},{"code":"46223","old_zip_code":"89702","zip_code":"8970221","prefecture_kana":"ｶｺﾞｼﾏｹﾝ","city_kana":"ﾐﾅﾐｷｭｳｼｭｳｼ","town_kana":"ｶﾜﾅﾍﾞﾁｮｳﾀﾍﾞﾀ","prefecture":"鹿児島県","city":"南九州市","town":"川辺町田部田","has_multiple_zip_codes":"0","needs_koaza":"0","has_chome":"0","shares_zip_code":"0","update_status":"0","change_reason":"0"},{"code":"46223","old_zip_code":"89702","zip_code":"8970222","prefecture_kana":"ｶｺﾞｼﾏｹﾝ","city_kana":"ﾐﾅﾐｷｭｳｼｭｳｼ","town_kana":"ｶﾜﾅﾍﾞﾁｮｳﾅｶﾞﾀ","prefecture":"鹿児島県","city":"南九州市","town":"川辺町永田","has_multiple_zip_codes":"0","needs_koaza":"0","has_chome":"0","shares_zip_code":"0","update_status":"0","change_reason":"0"},{"code":"46223","old_zip_code":"89701","zip_code":"8970132","prefecture_kana":"ｶｺﾞｼﾏｹﾝ","city_kana":"ﾐﾅﾐｷｭｳｼｭｳｼ","town_kana":"ｶﾜﾅﾍﾞﾁｮｳﾅｶﾔﾏﾀﾞ","prefecture":"鹿児島県","city":"南九州市","town":"川辺町中山田","has_multiple_zip_codes":"0","needs_koaza":"0","has_chome":"0","shares_zip_code":"0","update_status":"0","change_reason":"0"},{"code":"46223","old_zip_code":"89702","zip_code":"8970203","prefecture_kana":"ｶｺﾞｼﾏｹﾝ","city_kana":"ﾐﾅﾐｷｭｳｼｭｳｼ","town_kana":"ｶﾜﾅﾍﾞﾁｮｳﾉｻｷ","prefecture":"鹿児島県","city":"南九州市","town":"川辺町野崎","has_multiple_zip_codes":"0","needs_koaza":"0","has_chome":"0","shares_zip_code":"0","update_status":"0","change_reason":"0"},{"code":"46223","old_zip_code":"89702","zip_code":"8970205","prefecture_kana":"ｶｺﾞｼﾏｹﾝ","city_kana":"ﾐﾅﾐｷｭｳｼｭｳｼ","town_kana":"ｶﾜﾅﾍﾞﾁｮｳﾉﾏ","prefecture":"鹿児島県","city":"南九州市","town":"川辺町野間","has_multiple_zip_codes":"0","needs_koaza":"0","has_chome":"0","shares_zip_code":"0","update_status":"0","change_reason":"0"},{"code":"46223","old_zip_code":"89702","zip_code":"8970215","prefecture_kana":"ｶｺﾞｼﾏｹﾝ","city_kana":"ﾐﾅﾐｷｭｳｼｭｳｼ","town_kana":"ｶﾜﾅﾍﾞﾁｮｳﾋﾗﾔﾏ","prefecture":"鹿児島県","city":"南九州市","town":"川辺町平山","has_multiple_zip_codes":"0","needs_koaza":"0","has_chome":"0","shares_zip_code":"0","update_status":"0","change_reason":"0"},{"code":"46223","old_zip_code":"89702","zip_code":"8970204","prefecture_kana":"ｶｺﾞｼﾏｹﾝ","city_kana":"ﾐﾅﾐｷｭｳｼｭｳｼ","town_kana":"ｶﾜﾅﾍﾞﾁｮｳﾌﾙﾄﾉ","prefecture":"鹿児島県","city":"南九州市","town":"川辺町古殿","has_multiple_zip_codes":"0","needs_koaza":"0","has_chome":"0","shares_zip_code":"0","update_status":"0","change_reason":"0"},{"code":"46223","old_zip_code":"89702","zip_code":"8970214","prefecture_kana":"ｶｺﾞｼﾏｹﾝ","city_kana":"ﾐﾅﾐｷｭｳｼｭｳｼ","town_kana":"ｶﾜﾅﾍﾞﾁｮｳﾐﾔ","prefecture":"鹿児島県","city":"南九州市","town":"川辺町宮","has_multiple_zip_codes":"0","needs_koaza":"0","has_chome":"0","shares_zip_code":"0","update_status":"0","change_reason":"0"},{"code":"46223","old_zip_code":"89702","zip_code":"8970224","prefecture_kana":"ｶｺﾞｼﾏｹﾝ","city_kana":"ﾐﾅﾐｷｭｳｼｭｳｼ","town_kana":"ｶﾜﾅﾍﾞﾁｮｳﾓﾄﾍﾞｯﾌﾟ","prefecture":"鹿児島県","city":"南九州市","town":"川辺町本別府","has_multiple_zip_codes":"0","needs_koaza":"0","has_chome":"0","shares_zip_code":"0","update_status":"0","change_reason":"0"},{"code":"46223","old_zip_code":"89702","zip_code":"8970211","prefecture_kana":"ｶｺﾞｼﾏｹﾝ","city_kana":"ﾐﾅﾐｷｭｳｼｭｳｼ","town_kana":"ｶﾜﾅﾍﾞﾁｮｳﾘｮｳｿﾞｴ","prefecture":"鹿児島県","city":"南九州市","town":"川辺町両添","has_multiple_zip_codes":"0","needs_koaza":"0","has_chome":"0","shares_zip_code":"0","update_status":"0","change_reason":"0"},{"code":"46223","old_zip_code":"89703","zip_code":"8970301","prefecture_kana":"ｶｺﾞｼﾏｹﾝ","city_kana":"ﾐﾅﾐｷｭｳｼｭｳｼ","town_kana":"ﾁﾗﾝﾁｮｳｱﾂﾁ","prefecture":"鹿児島県","city":"南九州市","town":"知覧町厚地","has_multiple_zip_codes":"0","needs_koaza":"0","has_chome":"0","shares_zip_code":"0","update_status":"0","change_reason":"0"},{"code":"46223","old_zip_code":"89703","zip_code":"8970302","prefecture_kana":"ｶｺﾞｼﾏｹﾝ","city_kana":"ﾐﾅﾐｷｭｳｼｭｳｼ","town_kana":"ﾁﾗﾝﾁｮｳｺｵﾘ","prefecture":"鹿児島県","city":"南九州市","town":"知覧町郡","has_multiple_zip_codes":"0","needs_koaza":"0","has_chome":"0","shares_zip_code":"0","update_status":"0","change_reason":"0"},{"code":"46223","old_zip_code":"89703","zip_code":"8970305","prefecture_kana":"ｶｺﾞｼﾏｹﾝ","city_kana":"ﾐﾅﾐｷｭｳｼｭｳｼ","town_kana":"ﾁﾗﾝﾁｮｳｾｾ","prefecture":"鹿児島県","city":"南九州市","town":"知覧町瀬世","has_multiple_zip_codes":"0","needs_koaza":"0","has_chome":"0","shares_zip_code":"0","update_status":"0","change_reason":"0"},{"code":"46223","old_zip_code":"89703","zip_code":"8970303","prefecture_kana":"ｶｺﾞｼﾏｹﾝ","city_kana":"ﾐﾅﾐｷｭｳｼｭｳｼ","town_kana":"ﾁﾗﾝﾁｮｳﾅｶﾞｻﾄ","prefecture":"鹿児島県","city":"南九州市","town":"知覧町永里","has_multiple_zip_codes":"0","needs_koaza":"0","has_chome":"0","shares_zip_code":"0","update_status":"0","change_reason":"0"},{"code":"46223","old_zip_code":"89703","zip_code":"8970306","prefecture_kana":"ｶｺﾞｼﾏｹﾝ","city_kana":"ﾐﾅﾐｷｭｳｼｭｳｼ","town_kana":"ﾁﾗﾝﾁｮｳﾆｼﾓﾄ","prefecture":"鹿児島県","city":"南九州市","town":"知覧町西元","has_multiple_zip_codes":"0","needs_koaza":"0","has_chome":"0","shares_zip_code":"0","update_status":"0","change_reason":"0"},{"code":"46223","old_zip_code":"89703","zip_code":"8970304","prefecture_kana":"ｶｺﾞｼﾏｹﾝ","city_kana":"ﾐﾅﾐｷｭｳｼｭｳｼ","town_kana":"ﾁﾗﾝﾁｮｳﾋｶﾞｼﾍﾞｯﾌﾟ","prefecture":"鹿児島県","city":"南九州市","town":"知覧町東別府","has_multiple_zip_codes":"0","needs_koaza":"0","has_chome":"0","shares_zip_code":"0","update_status":"0","change_reason":"0"}]